Workbook
Name Slicer_County: #N/A

Sheet Term 2 Population Data Colle...
A1: Date | B1: County | C1: Region | D1: Subregion | E1: School | G1: Please select your role | H1: What is your role/title? | I1: Which mode of data collection in Kobo did you use? | J1: Ranking | K1: How would you rate the overall data collection process? | L1: How would you rate the overall use of the tool? | M1: What went well? | N1: What could have been better? | O1: How can we improve? | P1: Any other notes or comments
A2: 46178 | B2: KIAMBU | C2: KIAMBU CENTRAL | D2: LIMURU 1 | E2: NYATARAGI PRIMARY - 9be87a9e-1890-4d96-a065-46cd82ef5772 | G2: SL/SC | I2: Online (Link) | K2: Good | L2: Good | M2: I was able to collect data on time so easily | N2: Getting the baseline population | O2: N.A | W2: =COUNTBLANK('clean data'!O2:O590) -> 86
A3: 46178 | B3: KISUMU | C3: WESTERN - KISUMU | D3: KISUMU | E3: ST. JOHN PAUL KUDHO PRIMARY, ECDE AND JUNIOR SECONDARY - 37f21ffd-63f8-4210-91d8-14b6618939e3 | G3: SL/SC | I3: Online (Link) | K3: Very Good | L3: Very Good | M3: It's very fast | N3: None | O3: We should be given enough time | P3: Good work
A4: 46178 | B4: KIAMBU | C4: KIAMBU WEST | D4: KIKUYU | E4: WAMBAA PRIMARY SCHOOL - 6eb9b529-26ed-4951-94ac-a0c02dc126b7 | G4: SL/SC | I4: Online (Link) | K4: Good | L4: Good | M4: Summation of the total students were done automatically | N4: The daily attendance report has been quite tricky to take since not all teachers are ready to cooperate.One day I went to get the attendance and was told attendance is same as yesterday yet the class had alot of empty seats. | O4: Simple totals section instead of the boys and girls totals.
A5: 46178 | B5: KIAMBU | C5: KIAMBU EAST | D5: KIAMBU | E5: KANGOYA PRIMARY AND JUNIOR SCHOOL - a38f6992-2295-4610-8322-a62a291c5917 | G5: SL/SC | I5: Online (Link) | K5: Good | L5: Good | M5: Great cooperation with the administration | N5: High rates of Abesentim really affects the accuracy of the data collected | O5: Good relations for accurate data with the administration
A6: 46178 | B6: KIAMBU | C6: KIAMBU WEST | D6: KIKUYU | E6: GIKAMBURA PRIMARY AND JUNIOR SCHOOL - 59c577e8-b581-44c2-8469-8447a39563a5 | G6: SL/SC | I6: Offline (Used the app) | K6: Good | L6: Good | M6: Seamless navigation. | N6: GPS location was challenging. | O6: N/A
A7: 46178 | B7: KAJIADO | C7: NAIROBI WEST | D7: KAJIADO-LANGATA | E7: NGONG TOWNSHIP COMPREHENSIVE - f98dd2fc-dbd5-4861-a488-d913d4373c02 | G7: SL/SC | I7: Online (Link) | K7: Very Good | L7: Very Good | M7: Easier to use | N7: I like the layout.No suggestion | O7: All is well | P7: No comment
A8: 46178 | B8: KIAMBU | C8: KIAMBU EAST | D8: RUIRU-JUJA | E8: ATHENA PRIMARY AND JUNIOR SECONDARY SCHOOL - 528d5744-6bda-428c-a146-97801509e900 | G8: SL/SC | I8: Offline (Used the app) | K8: Very Good | L8: Very Good | M8: It's easy to use as I just key in the number of kids in every class and it calculate the overall population | N8: The app is friendly and easy to use | O8: It would be nice if we could receive airtime during the period of data collection and other assignments so as it can be efficient more
A9: 46178 | B9: KIAMBU | C9: KIAMBU WEST | D9: KABETE | E9: RUKUBI COMPREHENSIVE SCHOOL - b5ae1034-a416-49b9-9c84-5d8a8e2907b3 | G9: SL/SC | I9: Offline (Used the app) | K9: Very Good | L9: Very Good | M9: It was an easy task | N9: Everything was ok on my side | O9: Nothing so far | P9: N/A
A10: 46178 | B10: KIAMBU | C10: KIAMBU EAST | D10: RUIRU-GITHUNGURI | E10: ST. GEORGE'S COMPREHENSIVE SCHOOL - RUIRU - 685a09dc-9347-4783-9f6e-217f523e955c | G10: SL/SC | I10: Online (Link) | K10: Good | L10: Good | M10: It was easy to use | N10: Ensure smooth transfer where when you send the data it doesn’t take you back to start afresh | O10: Ensure smooth running
A11: 46178 | B11: KAKAMEGA | C11: WESTERN - KAKAMEGA | D11: KAKAMEGA | E11: MWIYALA COMPREHENSIVE PRIMARY - 45fbb32c-9d08-47a1-be02-86fad952f6ba | G11: SL/SC | I11: Offline (Used the app) | K11: Good | L11: Good | M11: It's fast and more convenient | N11: Logging in sometimes is a problem | O11: Saving logging in details to avoid going through the whole process again when you want to feed in data | P11: N/A
A12: 46178 | B12: KIAMBU | C12: KIAMBU CENTRAL | D12: LIMURU 1 | E12: THIGIO PRIMARY SCHOOL - c4a5a62d-cea9-4bc4-a00e-7d46afe11d41 | G12: SL/SC | I12: Online (Link) | K12: Good | L12: Good | M12: It's quite easy to maneuver. And one cannot loose data once you leave the site. | N12: I was unable to access the maps coordinates on my phone thus had to use the terminal | O12: N/A | P12: N/A
A13: 46178 | B13: NAIROBI | C13: NAIROBI EAST | D13: EMBAKASI | E13: NCC EMBAKASI COMPREHENSIVE SCHOOL - b172881a-b3d3-4145-8c08-7d9c50334de7 | G13: SL/SC | I13: Offline (Used the app) | K13: Good | L13: Good | M13: The process of collecting was made easy because the documents were available | N13: Co ordination among teachers when collecting the registers | O13: Easy acquiring of the registers, | P13: None
A14: 46178 | B14: KAJIADO | C14: NAIROBI WEST | D14: KAJIADO-LANGATA | E14: OLOOLUA COMPREHENSIVE SCHOOL - 1f13a6ea-cdca-4150-95ce-f59e3734df46 | G14: SL/SC | I14: Online (Link) | K14: Good | L14: Very Good | M14: Comparing the total daily attendance and the total meals served daily as it is crucial to find the percentage of feeding kids. | N14: Collection of daily school attendance is challenging as some teachers don't update their registers daily. | O14: All is good. | P14: None.
A15: 46178 | B15: NAIROBI | C15: NAIROBI EAST | D15: EMBAKASI | E15: NAIROBI SOUTH PRIMARY - ec26124e-e324-48c0-a811-ed306d0aa4fe | G15: SL/SC | I15: Online (Link) | K15: Good | L15: Good | M15: Everything went on well without any hitches experienced. | N15: N/A | O15: N/A | P15: None
A16: 46178 | B16: NAIROBI | C16: NAIROBI EAST | D16: KASARANI | E16: TOM MBOYA PRIMARY AND JUNIOR SECONDRAY SCHOOL - 9b5b7024-b8e4-4b4b-b368-f06aabd56727 | G16: SL/SC | I16: Online (Link) | K16: Good | L16: Good | M16: Thwe option for entering just the total beside per class population | N16: Excluding the baseline population | O16: Exclude the baseline population | P16: So far so good
A17: 46178 | B17: KIAMBU | C17: KIAMBU EAST | D17: RUIRU-JUJA | E17: ST. FRANCIS MUGAI COMPREHENSIVE PRIMARY - 3ce53765-0450-4643-bd02-269a731cb199 | G17: SL/SC | I17: Offline (Used the app) | K17: Good | L17: Very Good | M17: The app was really efficient | N17: Collecting the registers, some teachers took long to submit | O17: An official document highlighting why we need the register could help speed up the process
A18: 46178 | B18: KIAMBU | C18: KIAMBU CENTRAL | D18: GITHUNGURI 1 | E18: GATHAITHI SECONDARY SCHOOL - 255cffef-41e6-4022-a3fa-de2fbe03ca3d | G18: Highschool Tapper | I18: Online (Link) | K18: Good | L18: Good | M18: I was enable to notice the overall school attendance per day | N18: If the population was more | O18: Create a site where we could get the percentage of attending students over the school's total population | P18: None
A19: 46178 | B19: MOMBASA | C19: COAST | D19: NYALI - MOMBASA | E19: BEDZIMBA COMPREHENSIVE SCHOOL - 41ba099b-2ca5-4603-b61f-e128fd0adaa4 | G19: SL/SC | I19: Offline (Used the app) | K19: Good | L19: Very Good | M19: Data was captured fast, but it would save time and accuracy if most of the parts were put in the same page i.e categorised into ECD, primary and junior school. | N19: A fewer pages would be great | O19: Compile the pages to make them a few ,like ECD pages, primary page,and jss page. | P19: All went well ✅👏🏿
A20: 46178 | B20: KIAMBU | C20: KIAMBU WEST | D20: KIKUYU | E20: P.C.E.A MAMA NGINA KENYATTA COMPREHENSIVE - 3b4154e1-4c19-449e-adbe-a0fb51714f9d | G20: SL/SC | I20: Offline (Used the app) | K20: Good | L20: Good | M20: That's a good tracking of the feeding growth | N20: For me the head of institution declined to give me population thus requesting for a better communication with the head of institution for a professional documents to support the population collection | O20: In the schools that are declining to give the population then there should be a more conquering documents to request for a population | P20: No
A21: 46178 | B21: MOMBASA | C21: COAST | D21: NYALI - MOMBASA | E21: KONGOWEA PRIMARY SCHOOL - e180a289-0e43-4117-b925-e9a571ec3723 | G21: SL/SC | I21: Online (Link) | K21: Very Good | L21: Very Good | M21: It was so accurate. | N21: Apart from it being efficient and fast ... I don't see any change that will make it more better than it is at the moment. | O21: Everything is top-notch.. thank you team. | P21: All is well
A22: 46178 | B22: MOMBASA | C22: COAST | D22: NYALI - MOMBASA | E22: MTOPANGA COMPREHENSIVE SCHOOL - a30e43e4-ec3e-4e0c-a53c-1b37ae9635c1 | G22: SL/SC | I22: Offline (Used the app) | K22: Very Good | L22: Very Good | M22: Everything went well,the application is user friendly and the fact that you can save the data and edit before submitting that helps us so much | N22: Every thing was better on my side | O22: N/A
A23: 46178 | B23: NAIROBI | C23: NAIROBI EAST | D23: KASARANI | E23: CHELETA PRIMARY SCHOOL - a68bf13e-0d4c-4027-80ef-d68df2e5fddb | G23: SL/SC | I23: Online (Link) | K23: Good | L23: Good | M23: At some point i could, my school location was not picking the latitude .the location pick up was the major hinderance | N23: App is clear and to the point | O23: Enhance quick access for location. | P23: Good collection tool.
A24: 46178 | B24: NAIROBI | C24: NAIROBI WEST | D24: KIBRA-WESTLANDS | E24: ARYA PRIMARY SCHOOL - 1237de6d-87e5-4684-826d-c39a62256eb2 | G24: SL/SC | I24: Online (Link) | K24: Very Good | L24: Very Good | M24: The process was easy by the help of the kopo data collection tool, it was easy because after getting the data from the admin, I was only feeding it to the tool. | N24: Maybe next time you give us more time because, sometimes after collecting data you find that there are other students who wants to be admitted in school. Maybe next time we should submit data after midterm | O24: Add more time to the data collection exercise | P24: It was a smooth exercise
A25: 46178 | B25: MOMBASA | C25: COAST | D25: NYALI - MOMBASA | E25: AZHAR SHARRIF COMPREHENSIVE SCHOOL - 5120ef21-54c3-4761-9f55-6de14fc8afae | G25: SL/SC | I25: Online (Link) | K25: Very Good | L25: Very Good | M25: the whole process went well | N25: N/A | O25: Scale fusion is preventing the use of Kobocollect
A26: 46178 | B26: MOMBASA | C26: COAST | D26: GOME - MOMBASA | E26: LONGO PRIMARY SCHOOL - d1229365-3e34-4c2f-b6e4-4a16f1bac01a | G26: SL/SC | I26: Online (Link) | K26: Good | L26: Good | M26: Teachers cooperation was of top notch | N26: The app had problem in submitting the data | O26: Make it better
A27: 46178 | B27: BUNGOMA | C27: WESTERN - BUNGOMA | D27: BUNGOMA | E27: SIRITANYI RC COMPREHENSIVE SCHOOL - 5e64ac8f-8770-4ec5-ad3c-c2e5d31034cb | G27: SL/SC | I27: Offline (Used the app) | K27: Very Good | L27: Very Good | M27: This round it was sufficient, no more searching errors unlike the one we used in first term | N27: Transfers of kids, coming in and some some getting to other schools | O27: It should capture longitude anywhere,as long as you are in school compound not necessarily at the gate. | P27: N/A
A28: 46178 | B28: KIAMBU | C28: KIAMBU WEST | D28: KIKUYU | E28: NGURIUNDITU PRIMARY AND JUNIOR SCHOOL - 7b6eadba-2868-4967-911b-f7b6e46beba2 | G28: SL/SC | I28: Online (Link) | K28: Good | L28: Good | M28: Mine was fast.although I haven't tried doing it offline. | N28: It would be better if you asked us the overall number instead of ' number of boys and girls per class'. | O28: Already said in the previous question. | P28: Collecting the data daily is not working since we are being asked too much questions and it's becoming hectic , I propose we collect data may be once per month .
A29: 46178 | B29: MOMBASA | C29: COAST | D29: NYALI - MOMBASA | E29: MAWENI PRIMARY SCHOOL - df2872ff-b971-48a6-839c-32640be62ebc | G29: SL/SC | I29: Offline (Used the app) | K29: Very Good | L29: Very Good | M29: It was easy.the location was easy to allocate. | N29: None | O29: All was well | P29: It easy to operate and easy to understand
A30: 46178 | B30: KIAMBU | C30: KIAMBU CENTRAL | D30: LIMURU 1 | E30: TIEKUNU PRIMARY SCHOOL - 29cf51a0-aa46-4ed4-9c19-2014964f3670 | G30: SL/SC | I30: Offline (Used the app) | K30: Very Good | L30: Good | M30: Automatic calculation of numbers.easy to use both online and offline.saves unsent data in drafts to load later. | N30: Using offline maps since no easy offline from exact location | O30: So far so good,its easy to use | P30: None
A31: 46178 | B31: KISUMU | C31: WESTERN - KISUMU | D31: KISUMU | E31: KIBOS PRISON COMPREHENSIVE SCHOOL - 1ef6ff1c-475d-48d8-8a39-ca531bcc5ad9 | G31: SL/SC | I31: Offline (Used the app) | K31: Very Good | L31: Very Good | M31: The Kobo app is faster and easier to use since you can still save your work as draft and come back to continue. | N31: Improve on location pick up the app was a bit slower on picking the GPS. | O31: No recommendations for now. | P31: Collection of data has been made more easier compared to previous times were we had to take pictures from registers and scan then send.
A32: 46178 | B32: MOMBASA | C32: COAST | D32: NYALI - MOMBASA | E32: KISAUNI PRIMARY SCHOOL - 25ff122b-b892-4904-8b7c-cb9d74a7e1a0 | G32: SL/SC | I32: Offline (Used the app) | K32: Good | L32: Good | M32: Easy to use | N32: Accessibility was a bit hard at first. | O32: N/A | P32: None
A33: 46178 | B33: KIAMBU | C33: KIAMBU CENTRAL | D33: GITHUNGURI 2 | E33: KAMONDO PRIMARY AND JUNIOR SCHOOL - 085e4d09-08f2-4ee0-bb02-19a68da34b17 | G33: SL/SC | I33: Online (Link) | K33: Very Good | L33: Very Good | M33: The link is easier to use compared to the app. It provides a more direct process, as users can submit the form immediately after completing the required fields, without having to save it first before sending. | N33: N/A | O33: N/A | P33: No.
A34: 46178 | B34: NAIROBI | C34: NAIROBI WEST | D34: KIBRA-WESTLANDS | E34: ARYA PRIMARY SCHOOL - 1237de6d-87e5-4684-826d-c39a62256eb2 | G34: SL/SC | I34: Online (Link) | K34: Very Good | L34: Very Good | M34: The exercise was easy by the help of the kopo tool. | N34: It could be even better if u extended the data collection exercise to after midterm so as to capture all the students, some get admitted late | O34: Add more time to the exercise | P34: It was a smooth process
A35: 46178 | B35: NAIROBI | C35: NAIROBI EAST | D35: KASARANI | E35: DANDORA 1 PRIMARY AND JUNIOR SCHOOL - b9f3d61b-d58d-4d64-ac42-3db4d66eb585 | G35: SL/SC | I35: Online (Link) | K35: Poor | L35: Poor | M35: I was able to feed all the population data. | N35: I worked with the kobo app at first, after filling all the detailsand tried to submit, I got an error saying form is not active. Getting school GPS wasn't easier despite the fact that I was standing right at the school gate, I'm not even sure if the coordinates sent were accurate. After resorting to the online form, the major challenge was that I couldn't see what I was selecting as region, subregion and school, it's best if the wording appear clearly, not just some random circles. | O35: When you update the population collection tool on the app, please do us the courtesy of informing us so we can update as required. On the attachment, allow inclusion of more than 1 file type as well as multiple files, I didn't attach the evidence given by the ECDE Manager because there was no way to add it. In the list of source of information, you left out the ECDE manager, yet they are crucial in information provision, again, allow us to choose more than 1 source of information. I personally feel the GPS locator is so restricting, allow us to click and pick from the map if the auto detection feature fails. | P35: I have nothing more to share
A36: 46178 | B36: NAIROBI | C36: NAIROBI WEST | D36: KIBRA-WESTLANDS | E36: MUTHANGARI PRIMARY SCHOOL - 04c27057-afdb-4450-995b-a56cdc08cf0e | G36: SL/SC | I36: Online (Link) | K36: Very Good | L36: Very Good | M36: Population data collection was completed successfully within the set timeline. The Kobo tool was easy to use and navigate. Data submission was smooth with minimal technical challenges. Support from the team was readily available when needed. | N36: Intermittent internet connectivity affected synchronization in some instances. Some respondents required additional clarification on the data collection requirements. A few delays were experienced during data verification. | O36: Provide refresher training before future data collection exercises. Improve communication on timelines and expectations. Enhance offline functionality and synchronization speed. Share clear data collection guidelines in advance. | P36: Thank you for the support throughout the exercise. The process was well coordinated and provided valuable learning opportunities for future data collection activities.
A37: 46178 | B37: NAIROBI | C37: NAIROBI WEST | D37: DAGORETTI-WESTLANDS | E37: GITIBA PRIMARY AND E.C.D.E SCHOOL - 63d5639a-94a6-43c3-b1a5-b1fef2de82f3 | G37: SL/SC | I37: Online (Link) | K37: Poor | L37: Good | M37: The school administration was very supportive in sharing the population data. | N37: Kindly provide a letter or document indicating that the request is from Food for Education. This makes it easier when presenting it to the school administration, as they will clearly understand that it is an official request from F4E. | O37: Kindly provide a letter or document indicating that the request is from Food for Education. This makes it easier when presenting it to the school administration, as they will clearly understand that it is an official request from F4E.
A38: 46178 | B38: NAIROBI | C38: NAIROBI EAST | D38: KASARANI | E38: DANDORA DAY NURSERY - b1a11aad-0e1f-4c36-ab8d-7efe5c3a3c67 | G38: SL/SC | I38: Online (Link) | K38: Good | L38: Good | M38: My school being ECDE it's easy to identify who is not feeding and who is | N38: Show data for failed taps | O38: None | P38: None
A39: 46178 | B39: KIAMBU | C39: KIAMBU CENTRAL | D39: GITHUNGURI 1 | E39: MATHANJA PRIMARY SCHOOL - 8e59cca9-4a08-409f-8f9d-86bcf0cf8b40 | G39: SL/SC | I39: Online (Link) | K39: Very Good | L39: Very Good | M39: The fact that the totals were calculated easily | N39: Baseline population not all schools keep the records | O39: Avoid boys and girls total instead we write the total per class
A40: 46178 | B40: KISUMU | C40: WESTERN - KISUMU | D40: KISUMU | E40: KIBUYE MIXED PRIMARY SCHOOL - ce37a0bd-570c-4b7d-b9a8-b440f064790e | G40: SL/SC | I40: Online (Link) | K40: Good | L40: Good | M40: Collecting data per class | N40: To improve on efficiency of online link. Sometimes it's abit slow. | O40: To allow app to work offline | P40: I appreciate the app it more efficient than link.
A41: 46178 | B41: NAIROBI | C41: NAIROBI WEST | D41: KIBRA-WESTLANDS | E41: LOWER KABETE PRIMARY SCHOOL - 62a2829a-329f-4f94-8e67-01b54f86ce4d | G41: SL/SC | I41: Online (Link) | K41: Good | L41: Good | M41: Details of the population data that's needed | N41: Gps data collection; my phone has never got it ,so I do guess, I'd suggest this section should be optional | O41: Please let the gps data be optional and no a must | P41: Thank you
A42: 46178 | B42: NAIROBI | C42: NAIROBI EAST | D42: EMBAKASI | E42: MUGUMO DAY NURSERY - 98bd288a-da9c-47b8-be0a-4f76136cc3dd | G42: SL/SC | I42: Online (Link) | K42: Very Good | L42: Very Good | M42: The menu of cowpeas was well received. The parents are very supportive with the insufficient accounts being top up after following up the parents. | N42: The organization is working well from my end with great support from the PDA , KITCHEN MANAGER and the staff. | O42: I will really be greatful if I can get a server. | P42: The number of kids have stabilized.
A43: 46178 | B43: KAKAMEGA | C43: WESTERN - KAKAMEGA | D43: KAKAMEGA | E43: MATENDE CG PRIMARY - 8363c6a5-15d9-41e9-be69-fec9a147a440 | G43: SL/SC | I43: Offline (Used the app) | K43: Very Good | L43: Very Good | M43: The application is user friendly therefore making Data submission easy. | N43: N/A | O43: N/A | P43: N/A
A44: 46178 | B44: KIAMBU | C44: KIAMBU EAST | D44: KIAMBU | E44: TING'ANG'A H.G.M PRIMARY SCHOOL - 3a460c1d-a26e-44cd-9e02-c39c88d0e2fc | G44: SL/SC | I44: Online (Link) | K44: Very Good | L44: Very Good | M44: The link was was easy to use and input the data | N44: Nothing for now | O44: Nothing for now
A45: 46178 | B45: BUNGOMA | C45: WESTERN - BUNGOMA | D45: BUNGOMA | E45: ST. PETER'S NDENGELWA RC PRIMARY AND JUNIOR SCHOOL - 267c6dc4-9120-4daf-8ca6-5563a408a16c | G45: SL/SC | I45: Offline (Used the app) | K45: Good | L45: Very Good | M45: Easy to use. Data accessible if paused filling and needed to continue later | N45: One time password and url. After logging in details,the app should be leading you direct to the data and not key in url all the time | O45: Accessing the tool with the work email and password could be easier and convenient | P45: None
A46: 46178 | B46: MOMBASA | C46: COAST | D46: NYALI - MOMBASA | E46: KWA BULLO PRIMARY SCHOOL - 62e8d2ad-c82b-4248-a5ba-7541ebae5d6f | G46: SL/SC | I46: Online (Link) | K46: Good | L46: Very Good | M46: The Kobo app is fast and easy for someone to understand. The collection grew a great impact to understand the feeding pattern of the kids. | N46: The data it's not accurate some kids are out while collecting and some teachers they don't allow you in even if they know about the data Daly collection. | O46: The collection to be done fast week of the month and last week of the month. | P46: None
A47: 46178 | B47: KISUMU | C47: WESTERN - KISUMU | D47: KISUMU | E47: KASSAGAM PRIMARY, ECDE AND JUNIOR SCHOOL - c80a4eb5-ba11-49f8-9510-d8c7adecd9fc | G47: SL/SC | I47: Offline (Used the app) | K47: Good | L47: Very Good | M47: The process was smooth.it was well simplified | N47: Sometimes it's had to do a headcount in classes during lessons time.it interferes with the teaching programme | O47: I prefer the use of our population headcount data because it's always accurate as compared to the one given by the school administration | P47: None
A48: 46178 | B48: KIAMBU | C48: KIAMBU EAST | D48: RUIRU-JUJA | E48: GATONGORA COMPREHENSIVE SCHOOL - ce1d7f21-116d-4ba6-b939-4c15736cf796 | G48: SL/SC | I48: Offline (Used the app) | K48: Good | L48: Very Good | M48: The population collection tool is simplified. It is easy. | N48: N/A | O48: Allowing us to edit out mistakes even after saving the data. | P48: N/A
A49: 46178 | B49: KIAMBU | C49: KIAMBU WEST | D49: KIKUYU | E49: LUSIGETTI PRIMARY AND JUNIOR SCHOOL - 89ca0591-6262-4413-977c-9d4c16b4be4a | G49: SL/SC | I49: Online (Link) | K49: Very Good | L49: Very Good | M49: It is capturing data well. | N49: It's working well. | O49: It's good mode of data collection.
A50: 46178 | B50: KAKAMEGA | C50: WESTERN - KAKAMEGA | D50: KAKAMEGA | E50: ST. BASIL LURAMBI COMPREHENSIVE PRIMARY - a2644290-f83b-4450-884e-10731edde100 | G50: SL/SC | I50: Offline (Used the app) | K50: Very Good | L50: Very Good | M50: The Kobo connect app is very effective, collection and sending of the data was very very easy.I didn't encounter any challenges. | N50: I feel like since we already filled the base year population,there is no urgency of redoing it over and again.It is hard accessing this record from the school administration. | O50: I feel like the app is ok, continue with the nice work honestly.I am satisfied with it. | P50: I am more than pleased with the app,it is effective and simple to share the data.
A51: 46178 | B51: NAIROBI | C51: NAIROBI WEST | D51: KAJIADO-LANGATA | E51: LANG'ATA POLICE ECDE CENTRE - 8b07040e-44d5-41a6-a8dc-66644ef9c9d4 | G51: SL/SC | I51: Offline (Used the app) | K51: Very Good | L51: Very Good | M51: The tool was user friendly,easy to navigate and enabled efficient data collection. | N51: I did not encounter any challenges. | O51: The interface could be made more intuitive for first time users. | P51: N/A
A52: 46178 | B52: KIAMBU | C52: KIAMBU EAST | D52: RUIRU-JUJA | E52: THIKA PRIMARY SCHOOL - 92b0f217-aded-4f04-82a5-cb1d1724d1c7 | G52: SL/SC | I52: Offline (Used the app) | K52: Good | L52: Very Good | M52: The easy filling of data in kobo | N52: Honestly,the tool is vvery okay | O52: Give more training on using the same | P52: N/a
A53: 46178 | B53: KAKAMEGA | C53: WESTERN - KAKAMEGA | D53: KAKAMEGA | E53: FGCK DAISY SPECIAL PRIMARY - 9ffe9b9a-cae2-4c4d-abc3-a99d66e396ad | G53: SL/SC | I53: Offline (Used the app) | K53: Good | L53: Good | M53: Swift step by step process with user friendly interface and features. | N53: The process is swift | O53: Check on the upload process since my side can be submitted successfully yet on your end you don't have the data. | P53: Let's feed the future.
A54: 46178 | B54: KIAMBU | C54: KIAMBU CENTRAL | D54: GITHUNGURI 1 | E54: KIAWAIGURU PRIMARY SCHOOL - 8e230686-f774-49dc-85c4-124dd8f05a42 | G54: SL/SC | I54: Online (Link) | K54: Good | L54: Good | M54: It’s fast | N54: The part of collecting the location was slow | O54: Maybe change or remove the whole last part of asking the school location I found to be so slow yet I was outside and near the school gate I had to try like 3 different times | P54: None
A55: 46178 | B55: KAKAMEGA | C55: WESTERN - KAKAMEGA | D55: KAKAMEGA | E55: AMALEMBA PRIMARY SCHOOL - 0536aa10-96d2-40d3-86dc-a5bbeade6fb1 | G55: SL/SC | I55: Offline (Used the app) | K55: Good | L55: Good | M55: Auto save prevented data loss. The tool was user friendly. Data entry was fast and friendly. | N55: Personally I did not experience any challenge with the the app,once I entered my username and password everything went smoothly | O55: Inform the admin first before we go ahead collecting the data | P55: Our supervisor gave us a good demo on how to use the app and everyone completed the exercise
A56: 46178 | B56: MOMBASA | C56: COAST | D56: NYALI - MOMBASA | E56: KHADIJA PRIMARY SCHOOL - 279e0d3e-60e5-45c3-bdf0-504504e5c645 | G56: SL/SC | I56: Online (Link) | K56: Very Good | L56: Very Good | M56: Easier user interface and also you key in data with ease no repetitions | N56: Gps location to be obtained from anywhere within the school environment rather than going back to the entrance gate to capture it | O56: Improvements on when you have submitted the data if there can be away or a section where one can view the data he or she shared | P56: No comments
A57: 46178 | B57: MOMBASA | C57: COAST | D57: NYALI - MOMBASA | E57: FRERETOWN PRIMARY SCHOOL - 9aebd625-ef29-4732-acbc-8221383ae93c | G57: SL/SC | I57: Online (Link) | K57: Good | L57: Very Good | M57: Everything | N57: Nothing | O57: Satisfactory, no improvement needed. | P57: If the baseline population data is available in the F4E servers kindly avail it for me. The school administration here does not have have such data available in their records.
A58: 46178 | B58: KIAMBU | C58: KIAMBU EAST | D58: KIAMBU | E58: MACIRI COMPREHENSIVE SCHOOL - 848ba45a-fce6-4ef3-84dc-e64d24fa5998 | G58: SL/SC | I58: Online (Link) | K58: Good | L58: Good | M58: The link was easy to use unlike the app completely failed to upload | N58: The app;Having used the app before I prefer the app for me I find it easier and faster to use | O58: So far so good | P58: Overall it's a great and easy to use
A59: 46178 | B59: NAIROBI | C59: NAIROBI EAST | D59: EASTLEIGH-STAREHE | E59: NEW PUMWANI PRIMARY - 19015848-50bb-4ded-ba86-f26afdb223d9 | G59: SL/SC | I59: Online (Link) | K59: Good | L59: Very Good | M59: It was simple and efficient | N59: If a second attempt is made at submission of the data, the link should inform you that data is submitted and ask if one would like to make changes to the submitted data. | O59: When submitting data, the link should you to a new page showing the data has been successfully submitted. The page just refreshed itself on clicking submit and I found myself having to fill the form again | P59: None
A60: 46178 | B60: NAIROBI | C60: NAIROBI EAST | D60: EMBAKASI | E60: SIMBA DAY NURSERY - 0fd12f5c-0237-4625-b1a6-42f6a8965e23 | G60: SL/SC | I60: Online (Link) | K60: Very Good | L60: Very Good | M60: The administration trusted me with their records. | N60: More time to convince the administration that our intentions are right with their records. | O60: When discrepancies exits,bear with us and enough time to do the whole process again. | P60: It was a good exercise,I am able to know the number of learners not feeding and get the reason behind their action.
A61: 46178 | B61: NAIROBI | C61: NAIROBI WEST | D61: DAGORETTI-WESTLANDS | E61: KABETE VETLAB COMPREHENSIVE SCHOOL - 1480b05f-22e8-4e16-8cf2-e7cc230f5fff | G61: SL/SC | I61: Online (Link) | K61: Very Good | L61: Very Good | M61: It was so easy to navigate | N61: NA | O61: NA | P61: NA
... A72: 46178 | B72: BUNGOMA | C72: WESTERN - BUNGOMA | D72: BUNGOMA | E72: ST. ELIZABETH MUYAYI R.C - 97218157-c648-4885-bd79-3e4072f33f55 | G72: SL/SC | I72: Offline (Used the app) | K72: Very Good | L72: Very Good | M72: I gives you an opportunity to preview the data before sending | N72: The app is okay | O72: N/A | P72: N/A
A73: 46178 | B73: KIAMBU | C73: KIAMBU CENTRAL | D73: GITHUNGURI 1 | E73: P.C.E.A GATHAITHI AND JUNIOR SECONDARY SCHOOL - 80e831f8-25c3-4568-827b-fae0d0a990e0 | G73: SL/SC | I73: Online (Link) | K73: Very Good | L73: Very Good | M73: Kobo is user friendly. It is easy to work with. | N73: I had saved my data as draft but when I tried to find it, I couldn't access it. I ended up re- filling the data. | O73: Since kobo is user friendly, I am okay with it.
A74: 46178 | B74: KIAMBU | C74: KIAMBU CENTRAL | D74: LIMURU 1 | E74: ST. JOHN BOSCO PRIMARY - 2a7ffb15-e4e4-416d-bc2f-892f3899cce3 | G74: SL/SC | I74: Online (Link) | K74: Good | L74: Good | M74: Data collection process was clear.Tool was easy to use. | N74: Allow overall population count per class instead of separating boys and girls it consume alot of time . | O74: Allow us to do an overall class count instead of separating boys and girls. It will save time and reduce errors | P74: None
A75: 46178 | B75: KIAMBU | C75: KIAMBU CENTRAL | D75: LIMURU 1 | E75: GATUURA PRIMARY SCHOOL - b3b8358d-c99c-4d7d-91cb-69a1ab6cbe22 | G75: SL/SC | I75: Online (Link) | K75: Good | L75: Good | M75: Less typing,I.e it only involves inputting figures rather than typing,making it efficient. | N75: It was sluggish during uploading. There was a queue ,hence one is not sure whether their work is uploaded or not. | O75: Kindly let the response be prompt. To be sure the uploading is correct. | P75: N/A
A76: 46178 | B76: KIAMBU | C76: KIAMBU CENTRAL | D76: GITHUNGURI 1 | E76: GIKANG'A KAGECHE SECONDARY SCHOOL - bc9c77c7-6fd3-4f2d-a377-a2c217898f85 | G76: Highschool Tapper | I76: Online (Link) | K76: Good | L76: Good | M76: Number of students feeding remaining constant . | N76: Number of manual deduction still high (kids forgetting tags at home and parents refusing to top up for replacement).High failed taps due vulnerability | O76: Sponsorship-introduce Sponsorship to high-school students .Bring fruits to student to make their feeding great | P76: N/A
A77: 46178 | B77: MOMBASA | C77: COAST | D77: NYALI - MOMBASA | E77: PENTROSE COMMUNITY PRIMARY SCHOOL - 2a0f7ebd-98a8-4970-a9ee-7d057596a90f | G77: SL/SC | I77: Online (Link) | K77: Very Good | L77: Very Good | M77: There was unwaivering support and cooperation from the admin who provided me with the required accurate data. | N77: For the online link, it was taking too long to respond. | O77: Nothing. Everything was smooth and effective | P77: Both the app and online link are user-friendly which made the data collection process simple and effecient.
A78: 46178 | B78: KIAMBU | C78: KIAMBU EAST | D78: RUIRU-JUJA | E78: MUGUMOINI COMPREHENSIVE SCHOOL - 58e9a811-3045-4119-b9aa-0940449aa195 | G78: SL/SC | I78: Offline (Used the app) | K78: Very Good | L78: Very Good | M78: I appreciated being able to see the data before submitting. I liked how the steps were clear and in flow. | N78: For source of information, I would prefer being able to choose multiple sources | O78: We would appreciate data | P78: N/A
A79: 46178 | B79: MOMBASA | C79: COAST | D79: NYALI - MOMBASA | E79: BAMBURI PRIMARY SCHOOL - b5ebc6fd-b7b9-42ae-92aa-9e4342282304 | G79: SL/SC | I79: Offline (Used the app) | K79: Good | L79: Good | M79: It was the best method of data collection. It was the easiest method of data collection. | N79: Some of the admins didn't have baseline populations so it finds hard to get the baseline population. Some of the admins were busy so you have to be patient for a long time so that you can acquire the data. | O79: Give more time during search an exercise. Improve on the tool so that during the log in it should be easier rather than authaendicating everytime.e | P79: When improved on the tool is the most accurate tool i have ever used.
A80: 46178 | B80: KIAMBU | C80: KIAMBU EAST | D80: RUIRU-GITHUNGURI | E80: MWIHOKO COMPREHENSIVE SCHOOL - aea639a8-375f-4096-954d-9948d96597a1 | G80: SL/SC | I80: Offline (Used the app) | K80: Good | L80: Good | M80: Easy to use and understand | N80: Some schools do not have the baseline date but each time we take the population it still appears | O80: On my part the app was easy to use and made the exercise manageable
A81: 46178 | B81: KIAMBU | C81: KIAMBU EAST | D81: KIAMBU | E81: ACK RIABAI PRIMARY SCHOOL - b9207d35-fbf7-45ba-ad59-b07aef5c8303 | G81: SL/SC | I81: Online (Link) | K81: Very Good | L81: Very Good | M81: It was easily accessible. It stored data well without having to retype again. | N81: I didn't face any challenge with the online link. | O81: So far so good | P81: N/A
A82: 46178 | B82: KAKAMEGA | C82: WESTERN - KAKAMEGA | D82: KAKAMEGA | E82: ELUKHO PRIMARY SCHOOL - 1df3495b-40e1-4ae5-93bf-6e5f5c6581b1 | G82: SL/SC | I82: Offline (Used the app) | K82: Good | L82: Good | M82: When i went to School Admin (HOI) he cooperated and he asked senior teacher to take class registers and hand over the data in the registers. | N82: Timeline, when i say about timeline it means you gave a short period to collect the data like you find that senior teacher has classes to attend to then taking those registers from every teacher and it needs time so that we don't interfere with her lessons. | O82: Atleast you should be specific on matters of time atleast give allowance or give more time like two weeks. | P82: Then when it comes to the app atleast it should showing notification it requires update some core workers went though hard time .thank
A83: 46178 | B83: NAIROBI | C83: NAIROBI EAST | D83: EMBAKASI | E83: EDELVALE PRIMARY SCHOOL - 6d2b5efb-5470-4f4d-80dc-0aa214842d8a | G83: SL/SC | I83: Online (Link) | K83: Very Good | L83: Very Good | M83: Everything was good. | N83: None. | O83: It's okay. | P83: None
A84: 46178 | B84: KIAMBU | C84: KIAMBU EAST | D84: KIAMBU | E84: THINDIGUA PRIMARY SCHOOL - c83e3fb4-18ce-4e01-9a88-951ddecf305b | G84: SL/SC | I84: Online (Link) | K84: Good | L84: Good | M84: Accessibility | N84: Working on the kobo app for data collection | O84: Improve on the kobo app accessibility and effectiveness | P84: N/A
A85: 46178 | B85: NAIROBI | C85: NAIROBI WEST | D85: KAJIADO-LANGATA | E85: SHADRACK KIMALEL PRIMARY AND JUNIOR SCHOOL - e692a456-d8b0-4076-b3c9-81c8c7362829 | G85: SL/SC | I85: Offline (Used the app) | K85: Very Good | L85: Very Good | M85: What went well is that i can use the app when im offline because not all the times i have data.its fast.Its easier to use it. | N85: N/A | O85: N/A | P85: N/A
A86: 46178 | B86: NAIROBI | C86: NAIROBI EAST | D86: EMBAKASI | E86: TUMAINI PRIMARY AND JUNIOR SCHOOL - 322ca8c3-b579-4dd8-a7ab-347b79f078ef | G86: SL/SC | I86: Online (Link) | K86: Very Good | L86: Good | M86: Everything was smooth. I liked the fact that the progress is saved so you don't have to start afresh incase I exit abruptly. | N86: None. | O86: I don't think any improvement is needed. | P86: None.
A87: 46178 | B87: NAIROBI | C87: NAIROBI WEST | D87: KIBRA-WESTLANDS | E87: AGA KHAN PRIMARY SCHOOL - 8d19c9c9-e128-43de-9326-d93b09541029 | G87: SL/SC | I87: Online (Link) | K87: Good | L87: Good | M87: Well documented | N87: Some few challenges when it came to uploading of documents | O87: can improve on the process especially uploading of documents
A88: 46178 | B88: NAIROBI | C88: NAIROBI WEST | D88: KIBRA-WESTLANDS | E88: RAILA EDUCATIONAL CENTRE - 041937fb-b654-4989-ab59-2946a06d765f | G88: SL/SC | I88: Online (Link) | K88: Good | L88: Very Good | M88: The whole process was easy to understand and fill in. | N88: Do away with the school coordinates. May it apply only on a new school that is beginning the program. Can include a section where buy we do a survey on how many students at school level are registered under the program. | O88: I was suggesting that moving forward that under the baseline population of a school you indicated for us the number. That is the previous term population to help us compare the previous term and the current term. | P88: None
A89: 46178 | B89: KIAMBU | C89: KIAMBU WEST | D89: KIKUYU | E89: P.C.E.A THOGOTO PRIMARY AND JUNIOR SCHOOL - 5bab24d1-83ae-4a1e-8eb8-92b147a335b5 | G89: SL/SC | I89: Offline (Used the app) | K89: Good | L89: Good | M89: The form was user friendly. It guided. | N89: Nothing yet | O89: Nothing yet | P89: NA
A90: 46178 | B90: NAIROBI | C90: NAIROBI EAST | D90: EASTLEIGH-STAREHE | E90: HURUMA PRIMARY AND JUNIOR SECONDARY SCHOOL - b7140302-0102-4383-811e-a3cac7534323 | G90: SL/SC | I90: Online (Link) | K90: Very Good | L90: Very Good | M90: It's very fast and accurate . very easy to use | N90: It took a little longer when collecting the longitudes and latitudes | O90: May be next time we take the longitudes and latitudes from from the shades | P90: It's accuracy is top notch
A91: 46178 | B91: NAIROBI | C91: NAIROBI WEST | D91: KIBRA-WESTLANDS | E91: MILIMANI SCHOOL PRIMARY AND JUNIOR SECONDARY SCHOOL - 00f7fc9d-5709-4df2-a2d9-fba683cee2ad | G91: SL/SC | I91: Online (Link) | K91: Very Good | L91: Very Good | M91: The link is fast and efficient. | N91: I feel like the form is perfect the way it is because it's easier to fill | O91: I feel the form is perfect the way it is because it's fast
A92: 46178 | B92: MOMBASA | C92: COAST | D92: NYALI - MOMBASA | E92: KENGELENI PRIMARY SCHOOL - 13ac2cc3-46a7-4f21-a15d-09d0cf20dae9 | G92: SL/SC | I92: Offline (Used the app) | K92: Very Good | L92: Very Good | M92: Every step was leading to the next . All went well. | N92: During submission , it indicated that my file had an error. Later on I noticed that I did not download a new form thereafter I was able to submit my findings. | O92: I didn't not any point of improvement. | P92: I suggest that the program baseline should be stored online to avoid distortion when new admins assumes office .
A93: 46178 | B93: KISUMU | C93: WESTERN - KISUMU | D93: KISUMU | E93: KOSAWO PRIMARY, ECDE, EYE AND JUNIOR SECONDARY SCHOOL - bf395afa-8963-4793-a662-1b2306bb6ad2 | G93: SL/SC | I93: Online (Link) | K93: Very Good | L93: Good | M93: The administration was cooperate | N93: N/A | O93: Nothing everything is okay | P93: The Kobo app can be improved to make it more accessible and easier to use.
A94: 46178 | B94: KIAMBU | C94: KIAMBU CENTRAL | D94: LIMURU 1 | E94: BIBIRIONI PRIMARY SCHOOL - 36fdba40-b698-483a-b14c-9a1075e88a3c | G94: SL/SC | I94: Online (Link) | K94: Very Good | L94: Very Good | M94: Data collection was smooth as the admin was cooperative and supportive. I was able to cross checked the data given and it was very accurate. | N94: When browsing for a supportive document maybe you allow CamScanner because I had More than one document which need to be uploaded. | O94: A feature where we can access the record of the school population since the start of the program now the we have been uploading school population in a termly basis. | P94: An overall grade attendance when doing daily attendance because recording grade per grade girls and boys takes a lot of time.
A95: 46178 | B95: KIAMBU | C95: KIAMBU WEST | D95: KIKUYU | E95: KERWA PRIMARY AND JUNIOR SCHOOL - 0b50be2d-2cb6-49ca-bccd-70f14ef6912d | G95: SL/SC | I95: Online (Link) | K95: Good | L95: Good | M95: . The data collection was completed within the required timeline. The school management collaborated effectively throughout the exercise. | N95: Network challenges occasionally delayed data collection | O95: Provide offline data collection guidelines | P95: N/A
A96: 46178 | B96: KIAMBU | C96: KIAMBU CENTRAL | D96: LIMURU 1 | E96: GITUTHA PRIMARY SCHOOL - 52140973-5850-4ad1-aaf5-efc13bfa2896 | G96: SL/SC | I96: Online (Link) | K96: Good | L96: Very Good | M96: Data even when you are offline the data does not get lost | N96: none | O96: none | P96: none
A97: 46178 | B97: BUNGOMA | C97: WESTERN - BUNGOMA | D97: BUNGOMA | E97: WEKELEKHA R.C SCHOOL - 166f8ebb-9630-40df-8c8f-1de9eed1d273 | G97: SL/SC | I97: Online (Link) | K97: Good | L97: Good | M97: Parents understanding the accounts well and how to pay. | N97: For you and our bosses to work in counties and talk to parents who still have doubt. | O97: By continuing educating them through there phone , importance of this feeding. | P97: Good and much reliable food.
A98: 46178 | B98: NAIROBI | C98: NAIROBI WEST | D98: KIBRA-WESTLANDS | E98: KILIMANI PRIMARY AND JUNIOR SECONDARY SCHOOL - e19e0273-d832-4c6e-8044-5a3430a2a5be | G98: SL/SC | I98: Online (Link) | K98: Good | L98: Good | M98: Everything. I had no issue | N98: None | O98: For me it's working fine
A99: 46178 | B99: NAIROBI | C99: NAIROBI WEST | D99: KIBRA-WESTLANDS | E99: ISLAMIA COMPREHENSIVE PRIMARY - 78cf96bc-f2d3-4b50-a08f-8906bb835391 | G99: SL/SC | I99: Online (Link) | K99: Very Good | L99: Very Good | M99: The collection tool was easier to use than before tool | N99: No comment | O99: Make use of the app than the link
A100: 46178 | B100: NAIROBI | C100: NAIROBI WEST | D100: KIBRA-WESTLANDS | E100: MOI AVENUE PRIMARY SCHOOL - e907c4d3-4a0d-4626-9c3d-ce5ea59616fc | G100: SL/SC | I100: Online (Link) | K100: Good | L100: Very Good | M100: It's user friendly.Easier to input data | N100: N/A | O100: N/A
A101: 46178 | B101: KIAMBU | C101: KIAMBU EAST | D101: RUIRU-JUJA | E101: JUJA FARM PRIMARY SCHOOL - 0ed52eca-fb6a-4c33-b928-ed10bf935391 | G101: SL/SC | I101: Online (Link) | K101: Very Good | L101: Very Good | M101: Pretty easy to fill and understand | N101: It's great as it currently is | O101: N/A
A102: 46178 | B102: KIAMBU | C102: KIAMBU EAST | D102: RUIRU-GITHUNGURI | E102: KIMBO COMPREHENSIVE SCHOOL - e791e322-98b8-4cf9-bf55-e9bddfadd56c | G102: SL/SC | I102: Online (Link) | K102: Good | L102: Good | M102: The process was smooth with clear instructions | N102: N/A | O102: N/A | P102: N/A
A103: 46178 | B103: KIAMBU | C103: KIAMBU WEST | D103: KABETE | E103: KARURA PRIMARY SCHOOL - 0fc7c448-7cbb-4d4b-a20c-b1b4f81d8a98 | G103: SL/SC | I103: Online (Link) | K103: Very Good | L103: Very Good | M103: It was clear and understandable, also the ability to retrieve unfinished form was superb | N103: No challenge encountered | O103: N/A
A104: 46178 | B104: MOMBASA | C104: COAST | D104: GOME - MOMBASA | E104: GOME PRIMARY AND JUNIOR SCHOOL - a0aa4499-d731-4c32-9950-6a4c42af00a3 | G104: SL/SC | I104: Online (Link) | K104: Very Good | L104: Very Good | M104: Data collection was smooth.The tool was easy to use. | N104: Minor delays experienced during data collection. | O104: Enhancing user awareness and offer timely support where needed | P104: None
A105: 46178 | B105: MOMBASA | C105: COAST | D105: GOME - MOMBASA | E105: UMOJA PRIMARY SCHOOL - MOMBASA - 6127fbc1-5c4e-49ae-9f98-2519b6e460ce | G105: SL/SC | I105: Offline (Used the app) | K105: Very Good | L105: Very Good | M105: Everything went well it was easy to collect the data grade by grade. | N105: No challenges faced the admin gave maximum support with the activity. | O105: Nothing it's all good | P105: The exercise was successful from my end.
A106: 46178 | B106: NAIROBI | C106: NAIROBI EAST | D106: BIDII-ZAWADI REGION | E106: HESHIMA PRIMARY SCHOOL - dcfff6a0-6d63-4c80-93a0-a2f642f954e3 | G106: SL/SC | I106: Online (Link) | K106: Very Good | L106: Very Good | M106: It was easy to fill in the data of grades respectively | N106: Maybe put streams according to each school | O106: Adding streams | P106: None
A107: 46178 | B107: NAIROBI | C107: NAIROBI WEST | D107: KIBRA-WESTLANDS | E107: LAVINGTON PRIMARY SCHOOL - 78677b83-e42b-4d4f-8eeb-e37f5991dc15 | G107: SL/SC | I107: Online (Link) | K107: Good | L107: Good | M107: The system was okey and loading was easy | N107: All was well | O107: For now on my side i have no complain hence encouraging the company to continue with the good spirit of responsibility quickly to our issues | P107: The week has been well and the learners have been happy with the food quality and quantity
A108: 46178 | B108: NAIROBI | C108: NAIROBI EAST | D108: BIDII-ZAWADI REGION | E108: BAHATI DAY NURSERY - fa673598-f3b6-44c5-842a-3a702da07eb4 | G108: SL/SC | I108: Online (Link) | K108: Very Good | L108: Very Good | M108: It was easy to collect the population | N108: N/A | O108: N/A | P108: N/A
A109: 46178 | B109: NAIROBI | C109: NAIROBI EAST | D109: KASARANI | E109: NJATHA-INI PRIMARY AND JUNIOR SCHOOL - 507c9bed-6275-4476-9b00-b69b58388b75 | G109: SL/SC | I109: Online (Link) | K109: Good | L109: Good | M109: Easy to use and direct | N109: None | O109: None
A110: 46178 | B110: NAIROBI | C110: NAIROBI EAST | D110: KASARANI | E110: KARIOBANGI NORTH PRIMARY AND JUNIOR SCHOOL - 459a6d53-c301-49cf-a7a4-23fe92bf6369 | G110: SL/SC | I110: Online (Link) | K110: Very Good | L110: Very Good | M110: It's smooth and very fast | N110: Its becoming hard to get the baseline population | O110: Remove the baseline population f
...

Sheet clean data
A1: Date | B1: County | C1: Region | D1: Subregion | E1: School | F1: School Name Length | G1: Please select your role | H1: Which mode of data collection in Kobo did you use? | I1: How would you rate the overall data collection process? | J1: How would you rate the overall use of the tool? | K1: Process score | L1: Total Score | M1: Follow-up Required | N1: What went well? | O1: What could have been better? | P1: How can we improve? | Q1: Any other notes or comments
A2: 46178 | B2: KIAMBU | C2: KIAMBU CENTRAL | D2: LIMURU 1 | E2: NYATARAGI PRIMARY | F2: =LEN(E2) -> 17 | G2: SL/SC | H2: Online (Link) | I2: Good | J2: Good | K2: =IF(I2="Very Good",4,IF(I2="Good",3,IF(I2="Poor",2,IF(I2="Very Poor",1,"")))) -> 3 | L2: =IF(J2="Very Good",4,IF(J2="Good",3,IF(J2="Poor",2,IF(J2="Very Poor",1,"")))) -> 3 | M2: =IF(OR(I2="Poor",I2="Very Poor"),"YES","") | N2: I was able to collect data on time so easily | O2: Getting the baseline population | Y2: =COUNTBLANK(Q2:Q590) -> 378
A3: 46178 | B3: KISUMU | C3: WESTERN KISUMU | D3: KISUMU | E3: ST JOHN PAUL KUDHO PRIMARY ECDE AND JUNIOR SECONDARY | F3: =LEN(E3) -> 52 | G3: SL/SC | H3: Online (Link) | I3: Very Good | J3: Very Good | K3: =IF(I3="Very Good",4,IF(I3="Good",3,IF(I3="Poor",2,IF(I3="Very Poor",1,"")))) -> 4 | L3: =IF(J3="Very Good",4,IF(J3="Good",3,IF(J3="Poor",2,IF(J3="Very Poor",1,"")))) -> 4 | M3: =IF(OR(I3="Poor",I3="Very Poor"),"YES","") | N3: It's very fast | P3: We should be given enough time | Q3: Good work
A4: 46178 | B4: KIAMBU | C4: KIAMBU WEST | D4: KIKUYU | E4: WAMBAA PRIMARY SCHOOL | F4: =LEN(E4) -> 21 | G4: SL/SC | H4: Online (Link) | I4: Good | J4: Good | K4: =IF(I4="Very Good",4,IF(I4="Good",3,IF(I4="Poor",2,IF(I4="Very Poor",1,"")))) -> 3 | L4: =IF(J4="Very Good",4,IF(J4="Good",3,IF(J4="Poor",2,IF(J4="Very Poor",1,"")))) -> 3 | M4: =IF(OR(I4="Poor",I4="Very Poor"),"YES","") | N4: Summation of the total students were done automatically | O4: The daily attendance report has been quite tricky to take since not all teachers are ready to cooperateOne day I went to get the attendance and was told attendance is same as yesterday yet the class had alot of empty seats | P4: Simple totals section instead of the boys and girls totals
A5: 46178 | B5: KIAMBU | C5: KIAMBU EAST | D5: KIAMBU | E5: KANGOYA PRIMARY AND JUNIOR SCHOOL | F5: =LEN(E5) -> 33 | G5: SL/SC | H5: Online (Link) | I5: Good | J5: Good | K5: =IF(I5="Very Good",4,IF(I5="Good",3,IF(I5="Poor",2,IF(I5="Very Poor",1,"")))) -> 3 | L5: =IF(J5="Very Good",4,IF(J5="Good",3,IF(J5="Poor",2,IF(J5="Very Poor",1,"")))) -> 3 | M5: =IF(OR(I5="Poor",I5="Very Poor"),"YES","") | N5: Great cooperation with the administration | O5: High rates of Abesentim really affects the accuracy of the data collected | P5: Good relations for accurate data with the administration
A6: 46178 | B6: KIAMBU | C6: KIAMBU WEST | D6: KIKUYU | E6: GIKAMBURA PRIMARY AND JUNIOR SCHOOL | F6: =LEN(E6) -> 35 | G6: SL/SC | H6: Offline (Used the app) | I6: Good | J6: Good | K6: =IF(I6="Very Good",4,IF(I6="Good",3,IF(I6="Poor",2,IF(I6="Very Poor",1,"")))) -> 3 | L6: =IF(J6="Very Good",4,IF(J6="Good",3,IF(J6="Poor",2,IF(J6="Very Poor",1,"")))) -> 3 | M6: =IF(OR(I6="Poor",I6="Very Poor"),"YES","") | N6: Seamless vigation | O6: GPS location was challenging
A7: 46178 | B7: KAJIADO | C7: NAIROBI WEST | D7: KAJIADOm LANGATA | E7: NGONG TOWNSHIP COMPREHENSIVE | F7: =LEN(E7) -> 28 | G7: SL/SC | H7: Online (Link) | I7: Very Good | J7: Very Good | K7: =IF(I7="Very Good",4,IF(I7="Good",3,IF(I7="Poor",2,IF(I7="Very Poor",1,"")))) -> 4 | L7: =IF(J7="Very Good",4,IF(J7="Good",3,IF(J7="Poor",2,IF(J7="Very Poor",1,"")))) -> 4 | M7: =IF(OR(I7="Poor",I7="Very Poor"),"YES","") | N7: Easier to use | O7: I like the layoutNo suggestion | P7: All is well
A8: 46178 | B8: KIAMBU | C8: KIAMBU EAST | D8: RUIRUJUJA | E8: ATHE PRIMARY AND JUNIOR SECONDARY SCHOOL | F8: =LEN(E8) -> 40 | G8: SL/SC | H8: Offline (Used the app) | I8: Very Good | J8: Very Good | K8: =IF(I8="Very Good",4,IF(I8="Good",3,IF(I8="Poor",2,IF(I8="Very Poor",1,"")))) -> 4 | L8: =IF(J8="Very Good",4,IF(J8="Good",3,IF(J8="Poor",2,IF(J8="Very Poor",1,"")))) -> 4 | M8: =IF(OR(I8="Poor",I8="Very Poor"),"YES","") | N8: It's easy to use as I just key in the number of kids in every class and it calculate the overall population | O8: The app is friendly and easy to use | P8: It would be nice if we could receive airtime during the period of data collection and other assignments so as it can be efficient more
A9: 46178 | B9: KIAMBU | C9: KIAMBU WEST | D9: KABETE | E9: RUKUBI COMPREHENSIVE SCHOOL | F9: =LEN(E9) -> 27 | G9: SL/SC | H9: Offline (Used the app) | I9: Very Good | J9: Very Good | K9: =IF(I9="Very Good",4,IF(I9="Good",3,IF(I9="Poor",2,IF(I9="Very Poor",1,"")))) -> 4 | L9: =IF(J9="Very Good",4,IF(J9="Good",3,IF(J9="Poor",2,IF(J9="Very Poor",1,"")))) -> 4 | M9: =IF(OR(I9="Poor",I9="Very Poor"),"YES","") | N9: It was an easy task | O9: Everything was ok on my side | P9: so far
A10: 46178 | B10: KIAMBU | C10: KIAMBU EAST | D10: RUIRU GITHUNGURI | E10: ST GEORGE'S COMPREHENSIVE SCHOOL | F10: =LEN(E10) -> 32 | G10: SL/SC | H10: Online (Link) | I10: Good | J10: Good | K10: =IF(I10="Very Good",4,IF(I10="Good",3,IF(I10="Poor",2,IF(I10="Very Poor",1,"")))) -> 3 | L10: =IF(J10="Very Good",4,IF(J10="Good",3,IF(J10="Poor",2,IF(J10="Very Poor",1,"")))) -> 3 | M10: =IF(OR(I10="Poor",I10="Very Poor"),"YES","") | N10: It was easy to use | O10: Ensure smooth transfer where when you send the data it doesn’t take you back to start afresh | P10: Ensure smooth running
A11: 46178 | B11: KAKAMEGA | C11: WESTERN KAKAMEGA | D11: KAKAMEGA | E11: MWIYALA COMPREHENSIVE PRIMARY | F11: =LEN(E11) -> 29 | G11: SL/SC | H11: Offline (Used the app) | I11: Good | J11: Good | K11: =IF(I11="Very Good",4,IF(I11="Good",3,IF(I11="Poor",2,IF(I11="Very Poor",1,"")))) -> 3 | L11: =IF(J11="Very Good",4,IF(J11="Good",3,IF(J11="Poor",2,IF(J11="Very Poor",1,"")))) -> 3 | M11: =IF(OR(I11="Poor",I11="Very Poor"),"YES","") | N11: It's fast and more convenient | O11: Logging in sometimes is a problem | P11: Saving logging in details to avoid going through the whole process again when you want to feed in data
A12: 46178 | B12: KIAMBU | C12: KIAMBU CENTRAL | D12: LIMURU 1 | E12: THIGIO PRIMARY SCHOOL | F12: =LEN(E12) -> 21 | G12: SL/SC | H12: Online (Link) | I12: Good | J12: Good | K12: =IF(I12="Very Good",4,IF(I12="Good",3,IF(I12="Poor",2,IF(I12="Very Poor",1,"")))) -> 3 | L12: =IF(J12="Very Good",4,IF(J12="Good",3,IF(J12="Poor",2,IF(J12="Very Poor",1,"")))) -> 3 | M12: =IF(OR(I12="Poor",I12="Very Poor"),"YES","") | N12: It's quite easy to maneuver And one cannot loose data once you leave the site | O12: I was uble to access the maps coordites on my phone thus had to use the termil
A13: 46178 | B13: NAIROBI | C13: NAIROBI EAST | D13: EMBAKASI | E13: NCC EMBAKASI COMPREHENSIVE SCHOOL | F13: =LEN(E13) -> 33 | G13: SL/SC | H13: Offline (Used the app) | I13: Good | J13: Good | K13: =IF(I13="Very Good",4,IF(I13="Good",3,IF(I13="Poor",2,IF(I13="Very Poor",1,"")))) -> 3 | L13: =IF(J13="Very Good",4,IF(J13="Good",3,IF(J13="Poor",2,IF(J13="Very Poor",1,"")))) -> 3 | M13: =IF(OR(I13="Poor",I13="Very Poor"),"YES","") | N13: The process of collecting was made easy because the documents were available | O13: Co ordition among teachers when collecting the registers | P13: Easy acquiring of the registers
A14: 46178 | B14: KAJIADO | C14: NAIROBI WEST | D14: KAJIADO LANGATA | E14: OLOOLUA COMPREHENSIVE SCHOOL | F14: =LEN(E14) -> 28 | G14: SL/SC | H14: Online (Link) | I14: Good | J14: Very Good | K14: =IF(I14="Very Good",4,IF(I14="Good",3,IF(I14="Poor",2,IF(I14="Very Poor",1,"")))) -> 3 | L14: =IF(J14="Very Good",4,IF(J14="Good",3,IF(J14="Poor",2,IF(J14="Very Poor",1,"")))) -> 4 | M14: =IF(OR(I14="Poor",I14="Very Poor"),"YES","") | N14: Comparing the total daily attendance and the total meals served daily as it is crucial to find the percentage of feeding kids | O14: Collection of daily school attendance is challenging as some teachers don't update their registers daily | P14: All is good
A15: 46178 | B15: NAIROBI | C15: NAIROBI EAST | D15: EMBAKASI | E15: NAIROBI SOUTH PRIMARY | F15: =LEN(E15) -> 21 | G15: SL/SC | H15: Online (Link) | I15: Good | J15: Good | K15: =IF(I15="Very Good",4,IF(I15="Good",3,IF(I15="Poor",2,IF(I15="Very Poor",1,"")))) -> 3 | L15: =IF(J15="Very Good",4,IF(J15="Good",3,IF(J15="Poor",2,IF(J15="Very Poor",1,"")))) -> 3 | M15: =IF(OR(I15="Poor",I15="Very Poor"),"YES","") | N15: Everything went on well without any hitches experienced
A16: 46178 | B16: NAIROBI | C16: NAIROBI EAST | D16: KASARANI | E16: TOM MBOYA PRIMARY AND JUNIOR SECONDRAY SCHOOL | F16: =LEN(E16) -> 45 | G16: SL/SC | H16: Online (Link) | I16: Good | J16: Good | K16: =IF(I16="Very Good",4,IF(I16="Good",3,IF(I16="Poor",2,IF(I16="Very Poor",1,"")))) -> 3 | L16: =IF(J16="Very Good",4,IF(J16="Good",3,IF(J16="Poor",2,IF(J16="Very Poor",1,"")))) -> 3 | M16: =IF(OR(I16="Poor",I16="Very Poor"),"YES","") | N16: Thwe option for entering just the total beside per class population | O16: Excluding the baseline population | P16: Exclude the baseline population | Q16: So far so good
A17: 46178 | B17: KIAMBU | C17: KIAMBU EAST | D17: RUIRU JUJA | E17: ST FRANCIS MUGAI COMPREHENSIVE PRIMARY | F17: =LEN(E17) -> 38 | G17: SL/SC | H17: Offline (Used the app) | I17: Good | J17: Very Good | K17: =IF(I17="Very Good",4,IF(I17="Good",3,IF(I17="Poor",2,IF(I17="Very Poor",1,"")))) -> 3 | L17: =IF(J17="Very Good",4,IF(J17="Good",3,IF(J17="Poor",2,IF(J17="Very Poor",1,"")))) -> 4 | M17: =IF(OR(I17="Poor",I17="Very Poor"),"YES","") | N17: The app was really efficient | O17: Collecting the registers some teachers took long to submit | P17: An official document highlighting why we need the register could help speed up the process
A18: 46178 | B18: KIAMBU | C18: KIAMBU CENTRAL | D18: GITHUNGURI 1 | E18: GATHAITHI SECONDARY SCHOOL | F18: =LEN(E18) -> 26 | G18: Highschool Tapper | H18: Online (Link) | I18: Good | J18: Good | K18: =IF(I18="Very Good",4,IF(I18="Good",3,IF(I18="Poor",2,IF(I18="Very Poor",1,"")))) -> 3 | L18: =IF(J18="Very Good",4,IF(J18="Good",3,IF(J18="Poor",2,IF(J18="Very Poor",1,"")))) -> 3 | M18: =IF(OR(I18="Poor",I18="Very Poor"),"YES","") | N18: I was eble to notice the overall school attendance per day | O18: If the population was more | P18: Create a site where we could get the percentage of attending students over the school's total population
A19: 46178 | B19: MOMBASA | C19: COAST | D19: NYALI MOMBASA | E19: BEDZIMBA COMPREHENSIVE SCHOOL | F19: =LEN(E19) -> 29 | G19: SL/SC | H19: Offline (Used the app) | I19: Good | J19: Very Good | K19: =IF(I19="Very Good",4,IF(I19="Good",3,IF(I19="Poor",2,IF(I19="Very Poor",1,"")))) -> 3 | L19: =IF(J19="Very Good",4,IF(J19="Good",3,IF(J19="Poor",2,IF(J19="Very Poor",1,"")))) -> 4 | M19: =IF(OR(I19="Poor",I19="Very Poor"),"YES","") | N19: Data was captured fast but it would save time and accuracy if most of the parts were put in the same page ie categorised into ECD primary and junior school | O19: A fewer pages would be great | P19: Compile the pages to make them a few like ECD pages primary pageand jss page | Q19: All went well ✅👏🏿
A20: 46178 | B20: KIAMBU | C20: KIAMBU WEST | D20: KIKUYU | E20: PCEA MAMA NGI KENYATTA COMPREHENSIVE | F20: =LEN(E20) -> 36 | G20: SL/SC | H20: Offline (Used the app) | I20: Good | J20: Good | K20: =IF(I20="Very Good",4,IF(I20="Good",3,IF(I20="Poor",2,IF(I20="Very Poor",1,"")))) -> 3 | L20: =IF(J20="Very Good",4,IF(J20="Good",3,IF(J20="Poor",2,IF(J20="Very Poor",1,"")))) -> 3 | M20: =IF(OR(I20="Poor",I20="Very Poor"),"YES","") | N20: That's a good tracking of the feeding growth | O20: For me the head of institution declined to give me population thus requesting for a better communication with the head of institution for a professiol documents to support the population collection | P20: In the schools that are declining to give the population then there should be a more conquering documents to request for a population | Q20: No
A21: 46178 | B21: MOMBASA | C21: COAST | D21: NYALI MOMBASA | E21: KONGOWEA PRIMARY SCHOOL | F21: =LEN(E21) -> 23 | G21: SL/SC | H21: Online (Link) | I21: Very Good | J21: Very Good | K21: =IF(I21="Very Good",4,IF(I21="Good",3,IF(I21="Poor",2,IF(I21="Very Poor",1,"")))) -> 4 | L21: =IF(J21="Very Good",4,IF(J21="Good",3,IF(J21="Poor",2,IF(J21="Very Poor",1,"")))) -> 4 | M21: =IF(OR(I21="Poor",I21="Very Poor"),"YES","") | N21: It was so accurate | O21: Apart from it being efficient and fast I don't see any change that will make it more better than it is at the moment | P21: Everything is topnotch thank you team | Q21: All is well
A22: 46178 | B22: MOMBASA | C22: COAST | D22: NYALI MOMBASA | E22: MTOPANGA COMPREHENSIVE SCHOOL | F22: =LEN(E22) -> 29 | G22: SL/SC | H22: Offline (Used the app) | I22: Very Good | J22: Very Good | K22: =IF(I22="Very Good",4,IF(I22="Good",3,IF(I22="Poor",2,IF(I22="Very Poor",1,"")))) -> 4 | L22: =IF(J22="Very Good",4,IF(J22="Good",3,IF(J22="Poor",2,IF(J22="Very Poor",1,"")))) -> 4 | M22: =IF(OR(I22="Poor",I22="Very Poor"),"YES","") | N22: Everything went wellthe application is user friendly and the fact that you can save the data and edit before submitting that helps us so much | O22: Every thing was better on my side
A23: 46178 | B23: NAIROBI | C23: NAIROBI EAST | D23: KASARANI | E23: CHELETA PRIMARY SCHOOL | F23: =LEN(E23) -> 22 | G23: SL/SC | H23: Online (Link) | I23: Good | J23: Good | K23: =IF(I23="Very Good",4,IF(I23="Good",3,IF(I23="Poor",2,IF(I23="Very Poor",1,"")))) -> 3 | L23: =IF(J23="Very Good",4,IF(J23="Good",3,IF(J23="Poor",2,IF(J23="Very Poor",1,"")))) -> 3 | M23: =IF(OR(I23="Poor",I23="Very Poor"),"YES","") | N23: At some point i could my school location was not picking the latitude the location pick up was the major hinderance | O23: App is clear and to the point | P23: Enhance quick access for location | Q23: Good collection tool
A24: 46178 | B24: NAIROBI | C24: NAIROBI WEST | D24: KIBRAWESTLANDS | E24: ARYA PRIMARY SCHOOL | F24: =LEN(E24) -> 19 | G24: SL/SC | H24: Online (Link) | I24: Very Good | J24: Very Good | K24: =IF(I24="Very Good",4,IF(I24="Good",3,IF(I24="Poor",2,IF(I24="Very Poor",1,"")))) -> 4 | L24: =IF(J24="Very Good",4,IF(J24="Good",3,IF(J24="Poor",2,IF(J24="Very Poor",1,"")))) -> 4 | M24: =IF(OR(I24="Poor",I24="Very Poor"),"YES","") | N24: The process was easy by the help of the kopo data collection tool it was easy because after getting the data from the admin I was only feeding it to the tool | O24: Maybe next time you give us more time because sometimes after collecting data you find that there are other students who wants to be admitted in school Maybe next time we should submit data after midterm | P24: Add more time to the data collection exercise | Q24: It was a smooth exercise
A25: 46178 | B25: MOMBASA | C25: COAST | D25: NYALI MOMBASA | E25: AZHAR SHARRIF COMPREHENSIVE SCHOOL | F25: =LEN(E25) -> 34 | G25: SL/SC | H25: Online (Link) | I25: Very Good | J25: Very Good | K25: =IF(I25="Very Good",4,IF(I25="Good",3,IF(I25="Poor",2,IF(I25="Very Poor",1,"")))) -> 4 | L25: =IF(J25="Very Good",4,IF(J25="Good",3,IF(J25="Poor",2,IF(J25="Very Poor",1,"")))) -> 4 | M25: =IF(OR(I25="Poor",I25="Very Poor"),"YES","") | N25: the whole process went well | P25: Scale fusion is preventing the use of Kobocollect
A26: 46178 | B26: MOMBASA | C26: COAST | D26: GOME MOMBASA | E26: LONGO PRIMARY SCHOOL | F26: =LEN(E26) -> 20 | G26: SL/SC | H26: Online (Link) | I26: Good | J26: Good | K26: =IF(I26="Very Good",4,IF(I26="Good",3,IF(I26="Poor",2,IF(I26="Very Poor",1,"")))) -> 3 | L26: =IF(J26="Very Good",4,IF(J26="Good",3,IF(J26="Poor",2,IF(J26="Very Poor",1,"")))) -> 3 | M26: =IF(OR(I26="Poor",I26="Very Poor"),"YES","") | N26: Teachers cooperation was of top notch | O26: The app had problem in submitting the data | P26: Make it better
A27: 46178 | B27: BUNGOMA | C27: WESTERN BUNGOMA | D27: BUNGOMA | E27: SIRITANYI RC COMPREHENSIVE SCHOOL | F27: =LEN(E27) -> 33 | G27: SL/SC | H27: Offline (Used the app) | I27: Very Good | J27: Very Good | K27: =IF(I27="Very Good",4,IF(I27="Good",3,IF(I27="Poor",2,IF(I27="Very Poor",1,"")))) -> 4 | L27: =IF(J27="Very Good",4,IF(J27="Good",3,IF(J27="Poor",2,IF(J27="Very Poor",1,"")))) -> 4 | M27: =IF(OR(I27="Poor",I27="Very Poor"),"YES","") | N27: This round it was sufficient no more searching errors unlike the one we used in first term | O27: Transfers of kids coming in and some some getting to other schools | P27: It should capture longitude anywhereas long as you are in school compound not necessarily at the gate
A28: 46178 | B28: KIAMBU | C28: KIAMBU WEST | D28: KIKUYU | E28: NGURIUNDITU PRIMARY AND JUNIOR SCHOOL | F28: =LEN(E28) -> 37 | G28: SL/SC | H28: Online (Link) | I28: Good | J28: Good | K28: =IF(I28="Very Good",4,IF(I28="Good",3,IF(I28="Poor",2,IF(I28="Very Poor",1,"")))) -> 3 | L28: =IF(J28="Very Good",4,IF(J28="Good",3,IF(J28="Poor",2,IF(J28="Very Poor",1,"")))) -> 3 | M28: =IF(OR(I28="Poor",I28="Very Poor"),"YES","") | N28: Mine was fastalthough I haven't tried doing it offline | O28: It would be better if you asked us the overall number instead of ' number of boys and girls per class' | P28: Already said in the previous question | Q28: Collecting the data daily is not working since we are being asked too much questions and it's becoming hectic I propose we collect data may be once per month
A29: 46178 | B29: MOMBASA | C29: COAST | D29: NYALI MOMBASA | E29: MAWENI PRIMARY SCHOOL | F29: =LEN(E29) -> 21 | G29: SL/SC | H29: Offline (Used the app) | I29: Very Good | J29: Very Good | K29: =IF(I29="Very Good",4,IF(I29="Good",3,IF(I29="Poor",2,IF(I29="Very Poor",1,"")))) -> 4 | L29: =IF(J29="Very Good",4,IF(J29="Good",3,IF(J29="Poor",2,IF(J29="Very Poor",1,"")))) -> 4 | M29: =IF(OR(I29="Poor",I29="Very Poor"),"YES","") | N29: It was easythe location was easy to allocate | P29: All was well | Q29: It easy to operate and easy to understand
A30: 46178 | B30: KIAMBU | C30: KIAMBU CENTRAL | D30: LIMURU 1 | E30: TIEKUNU PRIMARY SCHOOL | F30: =LEN(E30) -> 22 | G30: SL/SC | H30: Offline (Used the app) | I30: Very Good | J30: Good | K30: =IF(I30="Very Good",4,IF(I30="Good",3,IF(I30="Poor",2,IF(I30="Very Poor",1,"")))) -> 4 | L30: =IF(J30="Very Good",4,IF(J30="Good",3,IF(J30="Poor",2,IF(J30="Very Poor",1,"")))) -> 3 | M30: =IF(OR(I30="Poor",I30="Very Poor"),"YES","") | N30: Automatic calculation of numberseasy to use both online and offlinesaves unsent data in drafts to load later | O30: Using offline maps since no easy offline from exact location | P30: So far so goodits easy to use
A31: 46178 | B31: KISUMU | C31: WESTERN KISUMU | D31: KISUMU | E31: KIBOS PRISON COMPREHENSIVE SCHOOL | F31: =LEN(E31) -> 33 | G31: SL/SC | H31: Offline (Used the app) | I31: Very Good | J31: Very Good | K31: =IF(I31="Very Good",4,IF(I31="Good",3,IF(I31="Poor",2,IF(I31="Very Poor",1,"")))) -> 4 | L31: =IF(J31="Very Good",4,IF(J31="Good",3,IF(J31="Poor",2,IF(J31="Very Poor",1,"")))) -> 4 | M31: =IF(OR(I31="Poor",I31="Very Poor"),"YES","") | N31: The Kobo app is faster and easier to use since you can still save your work as draft and come back to continue | O31: Improve on location pick up the app was a bit slower on picking the GPS | P31: No recommendations for now | Q31: Collection of data has been made more easier compared to previous times were we had to take pictures from registers and scan then send
A32: 46178 | B32: MOMBASA | C32: COAST | D32: NYALI MOMBASA | E32: KISAUNI PRIMARY SCHOOL | F32: =LEN(E32) -> 22 | G32: SL/SC | H32: Offline (Used the app) | I32: Good | J32: Good | K32: =IF(I32="Very Good",4,IF(I32="Good",3,IF(I32="Poor",2,IF(I32="Very Poor",1,"")))) -> 3 | L32: =IF(J32="Very Good",4,IF(J32="Good",3,IF(J32="Poor",2,IF(J32="Very Poor",1,"")))) -> 3 | M32: =IF(OR(I32="Poor",I32="Very Poor"),"YES","") | N32: Easy to use | O32: Accessibility was a bit hard at first
A33: 46178 | B33: KIAMBU | C33: KIAMBU CENTRAL | D33: GITHUNGURI 2 | E33: KAMONDO PRIMARY AND JUNIOR SCHOOL | F33: =LEN(E33) -> 33 | G33: SL/SC | H33: Online (Link) | I33: Very Good | J33: Very Good | K33: =IF(I33="Very Good",4,IF(I33="Good",3,IF(I33="Poor",2,IF(I33="Very Poor",1,"")))) -> 4 | L33: =IF(J33="Very Good",4,IF(J33="Good",3,IF(J33="Poor",2,IF(J33="Very Poor",1,"")))) -> 4 | M33: =IF(OR(I33="Poor",I33="Very Poor"),"YES","") | N33: The link is easier to use compared to the app It provides a more direct process as users can submit the form immediately after completing the required fields without having to save it first before sending | Q33: No
A34: 46178 | B34: NAIROBI | C34: NAIROBI WEST | D34: KIBRA WESTLANDS | E34: ARYA PRIMARY SCHOOL | F34: =LEN(E34) -> 19 | G34: SL/SC | H34: Online (Link) | I34: Very Good | J34: Very Good | K34: =IF(I34="Very Good",4,IF(I34="Good",3,IF(I34="Poor",2,IF(I34="Very Poor",1,"")))) -> 4 | L34: =IF(J34="Very Good",4,IF(J34="Good",3,IF(J34="Poor",2,IF(J34="Very Poor",1,"")))) -> 4 | M34: =IF(OR(I34="Poor",I34="Very Poor"),"YES","") | N34: The exercise was easy by the help of the kopo tool | O34: It could be even better if u extended the data collection exercise to after midterm so as to capture all the students some get admitted late | P34: Add more time to the exercise | Q34: It was a smooth process
A35: 46178 | B35: NAIROBI | C35: NAIROBI EAST | D35: KASARANI | E35: DANDORA 1 PRIMARY AND JUNIOR SCHOOL | F35: =LEN(E35) -> 35 | G35: SL/SC | H35: Online (Link) | I35: Poor | J35: Poor | K35: =IF(I35="Very Good",4,IF(I35="Good",3,IF(I35="Poor",2,IF(I35="Very Poor",1,"")))) -> 2 | L35: =IF(J35="Very Good",4,IF(J35="Good",3,IF(J35="Poor",2,IF(J35="Very Poor",1,"")))) -> 2 | M35: =IF(OR(I35="Poor",I35="Very Poor"),"YES","") -> YES | N35: I was able to feed all the population data | O35: I worked with the kobo app at first after filling all the detailsand tried to submit I got an error saying form is not active Getting school GPS wasn't easier despite the fact that I was standing right at the school gate I'm not even sure if the coordites sent were accurate After resorting to the online form the major challenge was that I couldn't see what I was selecting as region subregion and school it's best if the wording appear clearly not just some random circles | P35: When you update the population collection tool on the app please do us the courtesy of informing us so we can update as required On the attachment allow inclusion of more than 1 file type as well as multiple files I didn't attach the evidence given by the ECDE Mager because there was no way to add it In the list of source of information you left out the ECDE mager yet they are crucial in information provision again allow us to choose more than 1 source of information I persolly feel the GPS locator is so restricting allow us to click and pick from the map if the auto detection feature fails | Q35: I have more to share
A36: 46178 | B36: NAIROBI | C36: NAIROBI WEST | D36: KIBRA WESTLANDS | E36: MUTHANGARI PRIMARY SCHOOL | F36: =LEN(E36) -> 25 | G36: SL/SC | H36: Online (Link) | I36: Very Good | J36: Very Good | K36: =IF(I36="Very Good",4,IF(I36="Good",3,IF(I36="Poor",2,IF(I36="Very Poor",1,"")))) -> 4 | L36: =IF(J36="Very Good",4,IF(J36="Good",3,IF(J36="Poor",2,IF(J36="Very Poor",1,"")))) -> 4 | M36: =IF(OR(I36="Poor",I36="Very Poor"),"YES","") | N36: Population data collection was completed successfully within the set timeline The Kobo tool was easy to use and vigate Data submission was smooth with minimal technical challenges Support from the team was readily available when needed | O36: Intermittent internet connectivity affected synchronization in some instances Some respondents required additiol clarification on the data collection requirements A few delays were experienced during data verification | P36: Provide refresher training before future data collection exercises Improve communication on timelines and expectations Enhance offline functiolity and synchronization speed Share clear data collection guidelines in advance | Q36: Thank you for the support throughout the exercise The process was well coordited and provided valuable learning opportunities for future data collection activities
A37: 46178 | B37: NAIROBI | C37: NAIROBI WEST | D37: DAGORETTI WESTLANDS | E37: GITIBA PRIMARY AND ECDE SCHOOL | F37: =LEN(E37) -> 30 | G37: SL/SC | H37: Online (Link) | I37: Poor | J37: Good | K37: =IF(I37="Very Good",4,IF(I37="Good",3,IF(I37="Poor",2,IF(I37="Very Poor",1,"")))) -> 2 | L37: =IF(J37="Very Good",4,IF(J37="Good",3,IF(J37="Poor",2,IF(J37="Very Poor",1,"")))) -> 3 | M37: =IF(OR(I37="Poor",I37="Very Poor"),"YES","") -> YES | N37: The school administration was very supportive in sharing the population data | O37: Kindly provide a letter or document indicating that the request is from Food for Education This makes it easier when presenting it to the school administration as they will clearly understand that it is an official request from F4E | P37: Kindly provide a letter or document indicating that the request is from Food for Education This makes it easier when presenting it to the school administration as they will clearly understand that it is an official request from F4E
A38: 46178 | B38: NAIROBI | C38: NAIROBI EAST | D38: KASARANI | E38: DANDORA DAY NURSERY | F38: =LEN(E38) -> 19 | G38: SL/SC | H38: Online (Link) | I38: Good | J38: Good | K38: =IF(I38="Very Good",4,IF(I38="Good",3,IF(I38="Poor",2,IF(I38="Very Poor",1,"")))) -> 3 | L38: =IF(J38="Very Good",4,IF(J38="Good",3,IF(J38="Poor",2,IF(J38="Very Poor",1,"")))) -> 3 | M38: =IF(OR(I38="Poor",I38="Very Poor"),"YES","") | N38: My school being ECDE it's easy to identify who is not feeding and who is | O38: Show data for failed taps
A39: 46178 | B39: KIAMBU | C39: KIAMBU CENTRAL | D39: GITHUNGURI 1 | E39: MATHANJA PRIMARY SCHOOL | F39: =LEN(E39) -> 23 | G39: SL/SC | H39: Online (Link) | I39: Very Good | J39: Very Good | K39: =IF(I39="Very Good",4,IF(I39="Good",3,IF(I39="Poor",2,IF(I39="Very Poor",1,"")))) -> 4 | L39: =IF(J39="Very Good",4,IF(J39="Good",3,IF(J39="Poor",2,IF(J39="Very Poor",1,"")))) -> 4 | M39: =IF(OR(I39="Poor",I39="Very Poor"),"YES","") | N39: The fact that the totals were calculated easily | O39: Baseline population not all schools keep the records | P39: Avoid boys and girls total instead we write the total per class
A40: 46178 | B40: KISUMU | C40: WESTERN KISUMU | D40: KISUMU | E40: KIBUYE MIXED PRIMARY SCHOOL | F40: =LEN(E40) -> 27 | G40: SL/SC | H40: Online (Link) | I40: Good | J40: Good | K40: =IF(I40="Very Good",4,IF(I40="Good",3,IF(I40="Poor",2,IF(I40="Very Poor",1,"")))) -> 3 | L40: =IF(J40="Very Good",4,IF(J40="Good",3,IF(J40="Poor",2,IF(J40="Very Poor",1,"")))) -> 3 | M40: =IF(OR(I40="Poor",I40="Very Poor"),"YES","") | N40: Collecting data per class | O40: To improve on efficiency of online link Sometimes it's abit slow | P40: To allow app to work offline | Q40: I appreciate the app it more efficient than link
A41: 46178 | B41: NAIROBI | C41: NAIROBI WEST | D41: KIBRA WESTLANDS | E41: LOWER KABETE PRIMARY SCHOOL | F41: =LEN(E41) -> 27 | G41: SL/SC | H41: Online (Link) | I41: Good | J41: Good | K41: =IF(I41="Very Good",4,IF(I41="Good",3,IF(I41="Poor",2,IF(I41="Very Poor",1,"")))) -> 3 | L41: =IF(J41="Very Good",4,IF(J41="Good",3,IF(J41="Poor",2,IF(J41="Very Poor",1,"")))) -> 3 | M41: =IF(OR(I41="Poor",I41="Very Poor"),"YES","") | N41: Details of the population data that's needed | O41: Gps data collection; my phone has never got it so I do guess I'd suggest this section should be optiol | P41: Please let the gps data be optiol and no a must | Q41: Thank you
A42: 46178 | B42: NAIROBI | C42: NAIROBI EAST | D42: EMBAKASI | E42: MUGUMO DAY NURSERY | F42: =LEN(E42) -> 18 | G42: SL/SC | H42: Online (Link) | I42: Very Good | J42: Very Good | K42: =IF(I42="Very Good",4,IF(I42="Good",3,IF(I42="Poor",2,IF(I42="Very Poor",1,"")))) -> 4 | L42: =IF(J42="Very Good",4,IF(J42="Good",3,IF(J42="Poor",2,IF(J42="Very Poor",1,"")))) -> 4 | M42: =IF(OR(I42="Poor",I42="Very Poor"),"YES","") | N42: The menu of cowpeas was well received The parents are very supportive with the insufficient accounts being top up after following up the parents | O42: The organization is working well from my end with great support from the PDA KITCHEN MAGER and the staff | P42: I will really be greatful if I can get a server | Q42: The number of kids have stabilized
A43: 46178 | B43: KAKAMEGA | C43: WESTERN KAKAMEGA | D43: KAKAMEGA | E43: MATENDE CG PRIMARY | F43: =LEN(E43) -> 18 | G43: SL/SC | H43: Offline (Used the app) | I43: Very Good | J43: Very Good | K43: =IF(I43="Very Good",4,IF(I43="Good",3,IF(I43="Poor",2,IF(I43="Very Poor",1,"")))) -> 4 | L43: =IF(J43="Very Good",4,IF(J43="Good",3,IF(J43="Poor",2,IF(J43="Very Poor",1,"")))) -> 4 | M43: =IF(OR(I43="Poor",I43="Very Poor"),"YES","") | N43: The application is user friendly therefore making Data submission easy
A44: 46178 | B44: KIAMBU | C44: KIAMBU EAST | D44: KIAMBU | E44: TING'ANG'A HGM PRIMARY SCHOOL | F44: =LEN(E44) -> 29 | G44: SL/SC | H44: Online (Link) | I44: Very Good | J44: Very Good | K44: =IF(I44="Very Good",4,IF(I44="Good",3,IF(I44="Poor",2,IF(I44="Very Poor",1,"")))) -> 4 | L44: =IF(J44="Very Good",4,IF(J44="Good",3,IF(J44="Poor",2,IF(J44="Very Poor",1,"")))) -> 4 | M44: =IF(OR(I44="Poor",I44="Very Poor"),"YES","") | N44: The link was was easy to use and input the data | O44: for now | P44: for now
A45: 46178 | B45: BUNGOMA | C45: WESTERN BUNGOMA | D45: BUNGOMA | E45: ST PETER'S NDENGELWA RC PRIMARY AND JUNIOR SCHOOL | F45: =LEN(E45) -> 49 | G45: SL/SC | H45: Offline (Used the app) | I45: Good | J45: Very Good | K45: =IF(I45="Very Good",4,IF(I45="Good",3,IF(I45="Poor",2,IF(I45="Very Poor",1,"")))) -> 3 | L45: =IF(J45="Very Good",4,IF(J45="Good",3,IF(J45="Poor",2,IF(J45="Very Poor",1,"")))) -> 4 | M45: =IF(OR(I45="Poor",I45="Very Poor"),"YES","") | N45: Easy to use Data accessible if paused filling and needed to continue later | O45: One time password and url After logging in detailsthe app should be leading you direct to the data and not key in url all the time | P45: Accessing the tool with the work email and password could be easier and convenient
A46: 46178 | B46: MOMBASA | C46: COAST | D46: NYALI MOMBASA | E46: KWA BULLO PRIMARY SCHOOL | F46: =LEN(E46) -> 24 | G46: SL/SC | H46: Online (Link) | I46: Good | J46: Very Good | K46: =IF(I46="Very Good",4,IF(I46="Good",3,IF(I46="Poor",2,IF(I46="Very Poor",1,"")))) -> 3 | L46: =IF(J46="Very Good",4,IF(J46="Good",3,IF(J46="Poor",2,IF(J46="Very Poor",1,"")))) -> 4 | M46: =IF(OR(I46="Poor",I46="Very Poor"),"YES","") | N46: The Kobo app is fast and easy for someone to understand The collection grew a great impact to understand the feeding pattern of the kids | O46: The data it's not accurate some kids are out while collecting and some teachers they don't allow you in even if they know about the data Daly collection | P46: The collection to be done fast week of the month and last week of the month
A47: 46178 | B47: KISUMU | C47: WESTERN KISUMU | D47: KISUMU | E47: KASSAGAM PRIMARY ECDE AND JUNIOR SCHOOL | F47: =LEN(E47) -> 39 | G47: SL/SC | H47: Offline (Used the app) | I47: Good | J47: Very Good | K47: =IF(I47="Very Good",4,IF(I47="Good",3,IF(I47="Poor",2,IF(I47="Very Poor",1,"")))) -> 3 | L47: =IF(J47="Very Good",4,IF(J47="Good",3,IF(J47="Poor",2,IF(J47="Very Poor",1,"")))) -> 4 | M47: =IF(OR(I47="Poor",I47="Very Poor"),"YES","") | N47: The process was smoothit was well simplified | O47: Sometimes it's had to do a headcount in classes during lessons timeit interferes with the teaching programme | P47: I prefer the use of our population headcount data because it's always accurate as compared to the one given by the school administration
A48: 46178 | B48: KIAMBU | C48: KIAMBU EAST | D48: RUIRUJUJA | E48: GATONGORA COMPREHENSIVE SCHOOL | F48: =LEN(E48) -> 30 | G48: SL/SC | H48: Offline (Used the app) | I48: Good | J48: Very Good | K48: =IF(I48="Very Good",4,IF(I48="Good",3,IF(I48="Poor",2,IF(I48="Very Poor",1,"")))) -> 3 | L48: =IF(J48="Very Good",4,IF(J48="Good",3,IF(J48="Poor",2,IF(J48="Very Poor",1,"")))) -> 4 | M48: =IF(OR(I48="Poor",I48="Very Poor"),"YES","") | N48: The population collection tool is simplified It is easy | P48: Allowing us to edit out mistakes even after saving the data
A49: 46178 | B49: KIAMBU | C49: KIAMBU WEST | D49: KIKUYU | E49: LUSIGETTI PRIMARY AND JUNIOR SCHOOL | F49: =LEN(E49) -> 35 | G49: SL/SC | H49: Online (Link) | I49: Very Good | J49: Very Good | K49: =IF(I49="Very Good",4,IF(I49="Good",3,IF(I49="Poor",2,IF(I49="Very Poor",1,"")))) -> 4 | L49: =IF(J49="Very Good",4,IF(J49="Good",3,IF(J49="Poor",2,IF(J49="Very Poor",1,"")))) -> 4 | M49: =IF(OR(I49="Poor",I49="Very Poor"),"YES","") | N49: It is capturing data well | O49: It's working well | P49: It's good mode of data collection
A50: 46178 | B50: KAKAMEGA | C50: WESTERN KAKAMEGA | D50: KAKAMEGA | E50: ST BASIL LURAMBI COMPREHENSIVE PRIMARY | F50: =LEN(E50) -> 38 | G50: SL/SC | H50: Offline (Used the app) | I50: Very Good | J50: Very Good | K50: =IF(I50="Very Good",4,IF(I50="Good",3,IF(I50="Poor",2,IF(I50="Very Poor",1,"")))) -> 4 | L50: =IF(J50="Very Good",4,IF(J50="Good",3,IF(J50="Poor",2,IF(J50="Very Poor",1,"")))) -> 4 | M50: =IF(OR(I50="Poor",I50="Very Poor"),"YES","") | N50: The Kobo connect app is very effective collection and sending of the data was very very easyI didn't encounter any challenges | O50: I feel like since we already filled the base year populationthere is no urgency of redoing it over and againIt is hard accessing this record from the school administration | P50: I feel like the app is ok continue with the nice work honestlyI am satisfied with it | Q50: I am more than pleased with the appit is effective and simple to share the data
A51: 46178 | B51: NAIROBI | C51: NAIROBI WEST | D51: KAJIADO LANGATA | E51: LANG'ATA POLICE ECDE CENTRE | F51: =LEN(E51) -> 27 | G51: SL/SC | H51: Offline (Used the app) | I51: Very Good | J51: Very Good | K51: =IF(I51="Very Good",4,IF(I51="Good",3,IF(I51="Poor",2,IF(I51="Very Poor",1,"")))) -> 4 | L51: =IF(J51="Very Good",4,IF(J51="Good",3,IF(J51="Poor",2,IF(J51="Very Poor",1,"")))) -> 4 | M51: =IF(OR(I51="Poor",I51="Very Poor"),"YES","") | N51: The tool was user friendlyeasy to vigate and ebled efficient data collection | O51: I did not encounter any challenges | P51: The interface could be made more intuitive for first time users
A52: 46178 | B52: KIAMBU | C52: KIAMBU EAST | D52: RUIRU JUJA | E52: THIKA PRIMARY SCHOOL | F52: =LEN(E52) -> 20 | G52: SL/SC | H52: Offline (Used the app) | I52: Good | J52: Very Good | K52: =IF(I52="Very Good",4,IF(I52="Good",3,IF(I52="Poor",2,IF(I52="Very Poor",1,"")))) -> 3 | L52: =IF(J52="Very Good",4,IF(J52="Good",3,IF(J52="Poor",2,IF(J52="Very Poor",1,"")))) -> 4 | M52: =IF(OR(I52="Poor",I52="Very Poor"),"YES","") | N52: The easy filling of data in kobo | O52: Honestlythe tool is vvery okay | P52: Give more training on using the same
A53: 46178 | B53: KAKAMEGA | C53: WESTERN KAKAMEGA | D53: KAKAMEGA | E53: FGCK DAISY SPECIAL PRIMARY | F53: =LEN(E53) -> 26 | G53: SL/SC | H53: Offline (Used the app) | I53: Good | J53: Good | K53: =IF(I53="Very Good",4,IF(I53="Good",3,IF(I53="Poor",2,IF(I53="Very Poor",1,"")))) -> 3 | L53: =IF(J53="Very Good",4,IF(J53="Good",3,IF(J53="Poor",2,IF(J53="Very Poor",1,"")))) -> 3 | M53: =IF(OR(I53="Poor",I53="Very Poor"),"YES","") | N53: Swift step by step process with user friendly interface and features | O53: The process is swift | P53: Check on the upload process since my side can be submitted successfully yet on your end you don't have the data | Q53: Let's feed the future
A54: 46178 | B54: KIAMBU | C54: KIAMBU CENTRAL | D54: GITHUNGURI 1 | E54: KIAWAIGURU PRIMARY SCHOOL | F54: =LEN(E54) -> 25 | G54: SL/SC | H54: Online (Link) | I54: Good | J54: Good | K54: =IF(I54="Very Good",4,IF(I54="Good",3,IF(I54="Poor",2,IF(I54="Very Poor",1,"")))) -> 3 | L54: =IF(J54="Very Good",4,IF(J54="Good",3,IF(J54="Poor",2,IF(J54="Very Poor",1,"")))) -> 3 | M54: =IF(OR(I54="Poor",I54="Very Poor"),"YES","") | N54: It’s fast | O54: The part of collecting the location was slow | P54: Maybe change or remove the whole last part of asking the school location I found to be so slow yet I was outside and near the school gate I had to try like 3 different times
A55: 46178 | B55: KAKAMEGA | C55: WESTERN KAKAMEGA | D55: KAKAMEGA | E55: AMALEMBA PRIMARY SCHOOL | F55: =LEN(E55) -> 23 | G55: SL/SC | H55: Offline (Used the app) | I55: Good | J55: Good | K55: =IF(I55="Very Good",4,IF(I55="Good",3,IF(I55="Poor",2,IF(I55="Very Poor",1,"")))) -> 3 | L55: =IF(J55="Very Good",4,IF(J55="Good",3,IF(J55="Poor",2,IF(J55="Very Poor",1,"")))) -> 3 | M55: =IF(OR(I55="Poor",I55="Very Poor"),"YES","") | N55: Auto save prevented data loss The tool was user friendly Data entry was fast and friendly | O55: Persolly I did not experience any challenge with the the apponce I entered my userme and password everything went smoothly | P55: Inform the admin first before we go ahead collecting the data | Q55: Our supervisor gave us a good demo on how to use the app and everyone completed the exercise
A56: 46178 | B56: MOMBASA | C56: COAST | D56: NYALI MOMBASA | E56: KHADIJA PRIMARY SCHOOL | F56: =LEN(E56) -> 22 | G56: SL/SC | H56: Online (Link) | I56: Very Good | J56: Very Good | K56: =IF(I56="Very Good",4,IF(I56="Good",3,IF(I56="Poor",2,IF(I56="Very Poor",1,"")))) -> 4 | L56: =IF(J56="Very Good",4,IF(J56="Good",3,IF(J56="Poor",2,IF(J56="Very Poor",1,"")))) -> 4 | M56: =IF(OR(I56="Poor",I56="Very Poor"),"YES","") | N56: Easier user interface and also you key in data with ease no repetitions | O56: Gps location to be obtained from anywhere within the school environment rather than going back to the entrance gate to capture it | P56: Improvements on when you have submitted the data if there can be away or a section where one can view the data he or she shared | Q56: s
A57: 46178 | B57: MOMBASA | C57: COAST | D57: NYALI MOMBASA | E57: FRERETOWN PRIMARY SCHOOL | F57: =LEN(E57) -> 24 | G57: SL/SC | H57: Online (Link) | I57: Good | J57: Very Good | K57: =IF(I57="Very Good",4,IF(I57="Good",3,IF(I57="Poor",2,IF(I57="Very Poor",1,"")))) -> 3 | L57: =IF(J57="Very Good",4,IF(J57="Good",3,IF(J57="Poor",2,IF(J57="Very Poor",1,"")))) -> 4 | M57: =IF(OR(I57="Poor",I57="Very Poor"),"YES","") | N57: Everything | P57: Satisfactory no improvement needed | Q57: If the baseline population data is available in the F4E servers kindly avail it for me The school administration here does not have have such data available in their records
A58: 46178 | B58: KIAMBU | C58: KIAMBU EAST | D58: KIAMBU | E58: MACIRI COMPREHENSIVE SCHOOL | F58: =LEN(E58) -> 27 | G58: SL/SC | H58: Online (Link) | I58: Good | J58: Good | K58: =IF(I58="Very Good",4,IF(I58="Good",3,IF(I58="Poor",2,IF(I58="Very Poor",1,"")))) -> 3 | L58: =IF(J58="Very Good",4,IF(J58="Good",3,IF(J58="Poor",2,IF(J58="Very Poor",1,"")))) -> 3 | M58: =IF(OR(I58="Poor",I58="Very Poor"),"YES","") | N58: The link was easy to use unlike the app completely failed to upload | O58: The app;Having used the app before I prefer the app for me I find it easier and faster to use | P58: So far so good | Q58: Overall it's a great and easy to use
A59: 46178 | B59: NAIROBI | C59: NAIROBI EAST | D59: EASTLEIGH STAREHE | E59: NEW PUMWANI PRIMARY | F59: =LEN(E59) -> 19 | G59: SL/SC | H59: Online (Link) | I59: Good | J59: Very Good | K59: =IF(I59="Very Good",4,IF(I59="Good",3,IF(I59="Poor",2,IF(I59="Very Poor",1,"")))) -> 3 | L59: =IF(J59="Very Good",4,IF(J59="Good",3,IF(J59="Poor",2,IF(J59="Very Poor",1,"")))) -> 4 | M59: =IF(OR(I59="Poor",I59="Very Poor"),"YES","") | N59: It was simple and efficient | O59: If a second attempt is made at submission of the data the link should inform you that data is submitted and ask if one would like to make changes to the submitted data | P59: When submitting data the link should you to a new page showing the data has been successfully submitted The page just refreshed itself on clicking submit and I found myself having to fill the form again
A60: 46178 | B60: NAIROBI | C60: NAIROBI EAST | D60: EMBAKASI | E60: SIMBA DAY NURSERY | F60: =LEN(E60) -> 17 | G60: SL/SC | H60: Online (Link) | I60: Very Good | J60: Very Good | K60: =IF(I60="Very Good",4,IF(I60="Good",3,IF(I60="Poor",2,IF(I60="Very Poor",1,"")))) -> 4 | L60: =IF(J60="Very Good",4,IF(J60="Good",3,IF(J60="Poor",2,IF(J60="Very Poor",1,"")))) -> 4 | M60: =IF(OR(I60="Poor",I60="Very Poor"),"YES","") | N60: The administration trusted me with their records | O60: More time to convince the administration that our intentions are right with their records | P60: When discrepancies exitsbear with us and enough time to do the whole process again | Q60: It was a good exerciseI am able to know the number of learners not feeding and get the reason behind their action
A61: 46178 | B61: NAIROBI | C61: NAIROBI WEST | D61: DAGORETTI WESTLANDS | E61: KABETE VETLAB COMPREHENSIVE SCHOOL | F61: =LEN(E61) -> 34 | G61: SL/SC | H61: Online (Link) | I61: Very Good | J61: Very Good | K61: =IF(I61="Very Good",4,IF(I61="Good",3,IF(I61="Poor",2,IF(I61="Very Poor",1,"")))) -> 4 | L61: =IF(J61="Very Good",4,IF(J61="Good",3,IF(J61="Poor",2,IF(J61="Very Poor",1,"")))) -> 4 | M61: =IF(OR(I61="Poor",I61="Very Poor"),"YES","") | N61: It was so easy to vigate
A62: 46178 | B62: KAKAMEGA | C62: WESTERN KAKAMEGA | D62: KAKAMEGA | E62: EBUNG'AYA COMPREHENSIVE PRIMARY | F62: =LEN(E62) -> 31 | G62: SL/SC | H62: Offline (Used the app) | I62: Good | J62: Very Good | K62: =IF(I62="Very Good",4,IF(I62="Good",3,IF(I62="Poor",2,IF(I62="Very Poor",1,"")))) -> 3 | L62: =IF(J62="Very Good",4,IF(J62="Good",3,IF(J62="Poor",2,IF(J62="Very Poor",1,"")))) -> 4 | M62: =IF(OR(I62="Poor",I62="Very Poor"),"YES","") | N62: The headteacher gave me information on timeon time | O62: The app was not responding but called my PDA for assistance | P62: Before we take school population for the next term let the system be automatically updated that's for kobo tool | Q62: The process was good and kobo as a tool has make work easier at my end because it has break downs of school population per grade hence giving me upper hand to know I'm feeding these number in a certain grade and the population is these
A63: 46178 | B63: KIAMBU | C63: KIAMBU WEST | D63: KIKUYU | E63: GATAARA COMPREHENSIVE SCHOOL | F63: =LEN(E63) -> 28 | G63: SL/SC | H63: Online (Link) | I63: Very Good | J63: Good | K63: =IF(I63="Very Good",4,IF(I63="Good",3,IF(I63="Poor",2,IF(I63="Very Poor",1,"")))) -> 4 | L63: =IF(J63="Very Good",4,IF(J63="Good",3,IF(J63="Poor",2,IF(J63="Very Poor",1,"")))) -> 3 | M63: =IF(OR(I63="Poor",I63="Very Poor"),"YES","") | N63: I contacted head count persolly from grade to another and the exercise was awesome coz I interacted one on one with the learners and class teacher this got accurate numbers | O63: The exercise kind of caused interruption class timetable coz mostly i contacted the count during class time but wit he help of class teacher | P63: Introduce a edit option on the app in case of an error | Q63: this process has exposed a giant growth in the school which has been brought up by food for education foundation
A64: 46178 | B64: KIAMBU | C64: KIAMBU EAST | D64: KIAMBU | E64: BENSON NJAU PRIMARY SCHOOL | F64: =LEN(E64) -> 26 | G64: SL/SC | H64: Online (Link) | I64: Very Good | J64: Very Good | K64: =IF(I64="Very Good",4,IF(I64="Good",3,IF(I64="Poor",2,IF(I64="Very Poor",1,"")))) -> 4 | L64: =IF(J64="Very Good",4,IF(J64="Good",3,IF(J64="Poor",2,IF(J64="Very Poor",1,"")))) -> 4 | M64: =IF(OR(I64="Poor",I64="Very Poor"),"YES","") | N64: I was given all the details required so it was easy to answer the questions | O64: The type of questions asked | P64: Maybe next time let it have specific questions like if it is a primary school let it not have questions that belongs to secondary schools | Q64: No other comment
A65: 46178 | B65: KIAMBU | C65: KIAMBU EAST | D65: RUIRU JUJA | E65: KIBOKO COMPREHENSIVE SCHOOL | F65: =LEN(E65) -> 27 | G65: SL/SC | H65: Offline (Used the app) | I65: Good | J65: Very Good | K65: =IF(I65="Very Good",4,IF(I65="Good",3,IF(I65="Poor",2,IF(I65="Very Poor",1,"")))) -> 3 | L65: =IF(J65="Very Good",4,IF(J65="Good",3,IF(J65="Poor",2,IF(J65="Very Poor",1,"")))) -> 4 | M65: =IF(OR(I65="Poor",I65="Very Poor"),"YES","") | N65: Hoi is very supportive whenever I go to collect population dataThe data is precise correct and is given on time whenever she's there | O65: My biggest challenge is when the HOI is not in and the data has to be collected that daythe teacher some times are so relantant and I have to keep checking if they have given their numbers | P65: So far I haven't had any major challenge that I can't handle so we are okay | Q65: Some times I have issues with Kobo the last part where we have to get gps it keeps loading for long what can do about it
A66: 46178 | B66: KIAMBU | C66: KIAMBU EAST | D66: RUIRU JUJA | E66: GENERAL KAGO PRIMARY AND JUNIOR SECONDARY | F66: =LEN(E66) -> 41 | G66: SL/SC | H66: Offline (Used the app) | I66: Good | J66: Very Good | K66: =IF(I66="Very Good",4,IF(I66="Good",3,IF(I66="Poor",2,IF(I66="Very Poor",1,"")))) -> 3 | L66: =IF(J66="Very Good",4,IF(J66="Good",3,IF(J66="Poor",2,IF(J66="Very Poor",1,"")))) -> 4 | M66: =IF(OR(I66="Poor",I66="Very Poor"),"YES","") | N66: The Deputy Head Teacher had collected and documented the school population before hand so feeling the data was very easy | O66: The location part when using the link needs improvement because mine refused to fetch the coordites | P66: Give bundles because the task uses a lot
A67: 46178 | B67: KIAMBU | C67: KIAMBU CENTRAL | D67: LIMURU 1 | E67: RWAMBURI PRIMARY SCHOOL | F67: =LEN(E67) -> 23 | G67: SL/SC | H67: Offline (Used the app) | I67: Very Good | J67: Very Good | K67: =IF(I67="Very Good",4,IF(I67="Good",3,IF(I67="Poor",2,IF(I67="Very Poor",1,"")))) -> 4 | L67: =IF(J67="Very Good",4,IF(J67="Good",3,IF(J67="Poor",2,IF(J67="Very Poor",1,"")))) -> 4 | M67: =IF(OR(I67="Poor",I67="Very Poor"),"YES","") | N67: The app is easier to access and it is well arranged in any way you used to collect the population | O67: I didn't see any problem with the tool | P67: I didn't experience any issue while collecting data
A68: 46178 | B68: MOMBASA | C68: COAST | D68: NYALI MOMBASA | E68: MLALEO PRIMARY SCHOOL | F68: =LEN(E68) -> 21 | G68: SL/SC | H68: Online (Link) | I68: Good | J68: Good | K68: =IF(I68="Very Good",4,IF(I68="Good",3,IF(I68="Poor",2,IF(I68="Very Poor",1,"")))) -> 3 | L68: =IF(J68="Very Good",4,IF(J68="Good",3,IF(J68="Poor",2,IF(J68="Very Poor",1,"")))) -> 3 | M68: =IF(OR(I68="Poor",I68="Very Poor"),"YES","") | N68: Coordites were well captured | O68: In future while onboarding new schools baseline population should be captured by us/organisation This will save us from depending on administration for the information in which by the time it may not exist due to various factors | P68: Have for now | Q68: The work was done accordingly
A69: 46178 | B69: KAKAMEGA | C69: WESTERN KAKAMEGA | D69: KAKAMEGA | E69: MARABA MUNICIPALITY PRIMARY | F69: =LEN(E69) -> 27 | G69: SL/SC | H69: Offline (Used the app) | I69: Good | J69: Very Good | K69: =IF(I69="Very Good",4,IF(I69="Good",3,IF(I69="Poor",2,IF(I69="Very Poor",1,"")))) -> 3 | L69: =IF(J69="Very Good",4,IF(J69="Good",3,IF(J69="Poor",2,IF(J69="Very Poor",1,"")))) -> 4 | M69: =IF(OR(I69="Poor",I69="Very Poor"),"YES","") | N69: The deputy headteacher helped me in collecting the data | O69: The school admin and the teachers feel interrupted during their lessons | P69: Let the process not demand a lot of documents eg registers the admin is not willing to give us access to them | Q69: So far so goodthe program is running well
A70: 46178 | B70: NAIROBI | C70: NAIROBI WEST | D70: KAJIADO LANGATA | E70: MBAGATHI ROAD PRIMARY AND JUNIOR SECONDARY SCHOOL | F70: =LEN(E70) -> 49 | G70: SL/SC | H70: Online (Link) | I70: Good | J70: Good | K70: =IF(I70="Very Good",4,IF(I70="Good",3,IF(I70="Poor",2,IF(I70="Very Poor",1,"")))) -> 3 | L70: =IF(J70="Very Good",4,IF(J70="Good",3,IF(J70="Poor",2,IF(J70="Very Poor",1,"")))) -> 3 | M70: =IF(OR(I70="Poor",I70="Very Poor"),"YES","") | N70: The operation was very smooth | O70: Have the lasted data | P70: Talk to the HOI to always have updated list
A71: 46178 | B71: NAIROBI | C71: NAIROBI WEST | D71: DAGORETTI WESTLANDS | E71: KABIRIA ROAD PRIMARY AND JUNIOR SECONDARY SCHOOL | F71: =LEN(E71) -> 48 | G71: SL/SC | H71: Online (Link) | I71: Very Good | J71: Very Good | K71: =IF(I71="Very Good",4,IF(I71="Good",3,IF(I71="Poor",2,IF(I71="Very Poor",1,"")))) -> 4 | L71: =IF(J71="Very Good",4,IF(J71="Good",3,IF(J71="Poor",2,IF(J71="Very Poor",1,"")))) -> 4 | M71: =IF(OR(I71="Poor",I71="Very Poor"),"YES","") | N71: Efficiency and accuracy when collecting data | O71: For me it's good and easy to use | P71: Non | Q71: Non
A72: 46178 | B72: BUNGOMA | C72: WESTERN BUNGOMA | D72: BUNGOMA | E72: ST ELIZABETH MUYAYI RC | F72: =LEN(E72) -> 22 | G72: SL/SC | H72: Offline (Used the app) | I72: Very Good | J72: Very Good | K72: =IF(I72="Very Good",4,IF(I72="Good",3,IF(I72="Poor",2,IF(I72="Very Poor",1,"")))) -> 4 | L72: =IF(J72="Very Good",4,IF(J72="Good",3,IF(J72="Poor",2,IF(J72="Very Poor",1,"")))) -> 4 | M72: =IF(OR(I72="Poor",I72="Very Poor"),"YES","") | N72: I gives you an opportunity to preview the data before sending | O72: The app is okay
A73: 46178 | B73: KIAMBU | C73: KIAMBU CENTRAL | D73: GITHUNGURI 1 | E73: PCEA GATHAITHI AND JUNIOR SECONDARY SCHOOL | F73: =LEN(E73) -> 42 | G73: SL/SC | H73: Online (Link) | I73: Very Good | J73: Very Good | K73: =IF(I73="Very Good",4,IF(I73="Good",3,IF(I73="Poor",2,IF(I73="Very Poor",1,"")))) -> 4 | L73: =IF(J73="Very Good",4,IF(J73="Good",3,IF(J73="Poor",2,IF(J73="Very Poor",1,"")))) -> 4 | M73: =IF(OR(I73="Poor",I73="Very Poor"),"YES","") | N73: Kobo is user friendly It is easy to work with | O73: I had saved my data as draft but when I tried to find it I couldn't access it I ended up re filling the data | P73: Since kobo is user friendly I am okay with it
A74: 46178 | B74: KIAMBU | C74: KIAMBU CENTRAL | D74: LIMURU 1 | E74: ST JOHN BOSCO PRIMARY | F74: =LEN(E74) -> 21 | G74: SL/SC | H74: Online (Link) | I74: Good | J74: Good | K74: =IF(I74="Very Good",4,IF(I74="Good",3,IF(I74="Poor",2,IF(I74="Very Poor",1,"")))) -> 3 | L74: =IF(J74="Very Good",4,IF(J74="Good",3,IF(J74="Poor",2,IF(J74="Very Poor",1,"")))) -> 3 | M74: =IF(OR(I74="Poor",I74="Very Poor"),"YES","") | N74: Data collection process was clearTool was easy to use | O74: Allow overall population count per class instead of separating boys and girls it consume alot of time | P74: Allow us to do an overall class count instead of separating boys and girls It will save time and reduce errors
A75: 46178 | B75: KIAMBU | C75: KIAMBU CENTRAL | D75: LIMURU 1 | E75: GATUURA PRIMARY SCHOOL | F75: =LEN(E75) -> 22 | G75: SL/SC | H75: Online (Link) | I75: Good | J75: Good | K75: =IF(I75="Very Good",4,IF(I75="Good",3,IF(I75="Poor",2,IF(I75="Very Poor",1,"")))) -> 3 | L75: =IF(J75="Very Good",4,IF(J75="Good",3,IF(J75="Poor",2,IF(J75="Very Poor",1,"")))) -> 3 | M75: =IF(OR(I75="Poor",I75="Very Poor"),"YES","") | N75: Less typingIe it only involves inputting figures rather than typingmaking it efficient | O75: It was sluggish during uploading There was a queue hence one is not sure whether their work is uploaded or not | P75: Kindly let the response be prompt To be sure the uploading is correct
A76: 46178 | B76: KIAMBU | C76: KIAMBU CENTRAL | D76: GITHUNGURI 1 | E76: GIKANG'A KAGECHE SECONDARY SCHOOL | F76: =LEN(E76) -> 33 | G76: Highschool Tapper | H76: Online (Link) | I76: Good | J76: Good | K76: =IF(I76="Very Good",4,IF(I76="Good",3,IF(I76="Poor",2,IF(I76="Very Poor",1,"")))) -> 3 | L76: =IF(J76="Very Good",4,IF(J76="Good",3,IF(J76="Poor",2,IF(J76="Very Poor",1,"")))) -> 3 | M76: =IF(OR(I76="Poor",I76="Very Poor"),"YES","") | N76: Number of students feeding remaining constant | O76: Number of manual deduction still high (kids forgetting tags at home and parents refusing to top up for replacement)High failed taps due vulnerability | P76: Sponsorshipintroduce Sponsorship to highschool students Bring fruits to student to make their feeding great
A77: 46178 | B77: MOMBASA | C77: COAST | D77: NYALI MOMBASA | E77: PENTROSE COMMUNITY PRIMARY SCHOOL | F77: =LEN(E77) -> 33 | G77: SL/SC | H77: Online (Link) | I77: Very Good | J77: Very Good | K77: =IF(I77="Very Good",4,IF(I77="Good",3,IF(I77="Poor",2,IF(I77="Very Poor",1,"")))) -> 4 | L77: =IF(J77="Very Good",4,IF(J77="Good",3,IF(J77="Poor",2,IF(J77="Very Poor",1,"")))) -> 4 | M77: =IF(OR(I77="Poor",I77="Very Poor"),"YES","") | N77: There was unwaivering support and cooperation from the admin who provided me with the required accurate data | O77: For the online link it was taking too long to respond | P77: Everything was smooth and effective | Q77: Both the app and online link are userfriendly which made the data collection process simple and effecient
A78: 46178 | B78: KIAMBU | C78: KIAMBU EAST | D78: RUIRUJUJA | E78: MUGUMOINI COMPREHENSIVE SCHOOL | F78: =LEN(E78) -> 30 | G78: SL/SC | H78: Offline (Used the app) | I78: Very Good | J78: Very Good | K78: =IF(I78="Very Good",4,IF(I78="Good",3,IF(I78="Poor",2,IF(I78="Very Poor",1,"")))) -> 4 | L78: =IF(J78="Very Good",4,IF(J78="Good",3,IF(J78="Poor",2,IF(J78="Very Poor",1,"")))) -> 4 | M78: =IF(OR(I78="Poor",I78="Very Poor"),"YES","") | N78: I appreciated being able to see the data before submitting I liked how the steps were clear and in flow | O78: For source of information I would prefer being able to choose multiple sources | P78: We would appreciate data
A79: 46178 | B79: MOMBASA | C79: COAST | D79: NYALI MOMBASA | E79: BAMBURI PRIMARY SCHOOL | F79: =LEN(E79) -> 22 | G79: SL/SC | H79: Offline (Used the app) | I79: Good | J79: Good | K79: =IF(I79="Very Good",4,IF(I79="Good",3,IF(I79="Poor",2,IF(I79="Very Poor",1,"")))) -> 3 | L79: =IF(J79="Very Good",4,IF(J79="Good",3,IF(J79="Poor",2,IF(J79="Very Poor",1,"")))) -> 3 | M79: =IF(OR(I79="Poor",I79="Very Poor"),"YES","") | N79: It was the best method of data collection It was the easiest method of data collection | O79: Some of the admins didn't have baseline populations so it finds hard to get the baseline population Some of the admins were busy so you have to be patient for a long time so that you can acquire the data | P79: Give more time during search an exercise Improve on the tool so that during the log in it should be easier rather than authaendicating everytimee | Q79: When improved on the tool is the most accurate tool i have ever used
A80: 46178 | B80: KIAMBU | C80: KIAMBU EAST | D80: RUIRU GITHUNGURI | E80: MWIHOKO COMPREHENSIVE SCHOOL | F80: =LEN(E80) -> 28 | G80: SL/SC | H80: Offline (Used the app) | I80: Good | J80: Good | K80: =IF(I80="Very Good",4,IF(I80="Good",3,IF(I80="Poor",2,IF(I80="Very Poor",1,"")))) -> 3 | L80: =IF(J80="Very Good",4,IF(J80="Good",3,IF(J80="Poor",2,IF(J80="Very Poor",1,"")))) -> 3 | M80: =IF(OR(I80="Poor",I80="Very Poor"),"YES","") | N80: Easy to use and understand | O80: Some schools do not have the baseline date but each time we take the population it still appears | P80: On my part the app was easy to use and made the exercise mageable
A81: 46178 | B81: KIAMBU | C81: KIAMBU EAST | D81: KIAMBU | E81: ACK RIABAI PRIMARY SCHOOL | F81: =LEN(E81) -> 25 | G81: SL/SC | H81: Online (Link) | I81: Very Good | J81: Very Good | K81: =IF(I81="Very Good",4,IF(I81="Good",3,IF(I81="Poor",2,IF(I81="Very Poor",1,"")))) -> 4 | L81: =IF(J81="Very Good",4,IF(J81="Good",3,IF(J81="Poor",2,IF(J81="Very Poor",1,"")))) -> 4 | M81: =IF(OR(I81="Poor",I81="Very Poor"),"YES","") | N81: It was easily accessible It stored data well without having to retype again | O81: I didn't face any challenge with the online link | P81: So far so good
A82: 46178 | B82: KAKAMEGA | C82: WESTERN KAKAMEGA | D82: KAKAMEGA | E82: ELUKHO PRIMARY SCHOOL | F82: =LEN(E82) -> 21 | G82: SL/SC | H82: Offline (Used the app) | I82: Good | J82: Good | K82: =IF(I82="Very Good",4,IF(I82="Good",3,IF(I82="Poor",2,IF(I82="Very Poor",1,"")))) -> 3 | L82: =IF(J82="Very Good",4,IF(J82="Good",3,IF(J82="Poor",2,IF(J82="Very Poor",1,"")))) -> 3 | M82: =IF(OR(I82="Poor",I82="Very Poor"),"YES","") | N82: When i went to School Admin (HOI) he cooperated and he asked senior teacher to take class registers and hand over the data in the registers | O82: Timeline when i say about timeline it means you gave a short period to collect the data like you find that senior teacher has classes to attend to then taking those registers from every teacher and it needs time so that we don't interfere with her lessons | P82: Atleast you should be specific on matters of time atleast give allowance or give more time like two weeks | Q82: Then when it comes to the app atleast it should showing notification it requires update some core workers went though hard time thank
A83: 46178 | B83: NAIROBI | C83: NAIROBI EAST | D83: EMBAKASI | E83: EDELVALE PRIMARY SCHOOL | F83: =LEN(E83) -> 23 | G83: SL/SC | H83: Online (Link) | I83: Very Good | J83: Very Good | K83: =IF(I83="Very Good",4,IF(I83="Good",3,IF(I83="Poor",2,IF(I83="Very Poor",1,"")))) -> 4 | L83: =IF(J83="Very Good",4,IF(J83="Good",3,IF(J83="Poor",2,IF(J83="Very Poor",1,"")))) -> 4 | M83: =IF(OR(I83="Poor",I83="Very Poor"),"YES","") | N83: Everything was good | P83: It's okay
A84: 46178 | B84: KIAMBU | C84: KIAMBU EAST | D84: KIAMBU | E84: THINDIGUA PRIMARY SCHOOL | F84: =LEN(E84) -> 24 | G84: SL/SC | H84: Online (Link) | I84: Good | J84: Good | K84: =IF(I84="Very Good",4,IF(I84="Good",3,IF(I84="Poor",2,IF(I84="Very Poor",1,"")))) -> 3 | L84: =IF(J84="Very Good",4,IF(J84="Good",3,IF(J84="Poor",2,IF(J84="Very Poor",1,"")))) -> 3 | M84: =IF(OR(I84="Poor",I84="Very Poor"),"YES","") | N84: Accessibility | O84: Working on the kobo app for data collection | P84: Improve on the kobo app accessibility and effectiveness
A85: 46178 | B85: NAIROBI | C85: NAIROBI WEST | D85: KAJIADO LANGATA | E85: SHADRACK KIMALEL PRIMARY AND JUNIOR SCHOOL | F85: =LEN(E85) -> 42 | G85: SL/SC | H85: Offline (Used the app) | I85: Very Good | J85: Very Good | K85: =IF(I85="Very Good",4,IF(I85="Good",3,IF(I85="Poor",2,IF(I85="Very Poor",1,"")))) -> 4 | L85: =IF(J85="Very Good",4,IF(J85="Good",3,IF(J85="Poor",2,IF(J85="Very Poor",1,"")))) -> 4 | M85: =IF(OR(I85="Poor",I85="Very Poor"),"YES","") | N85: What went well is that i can use the app when im offline because not all the times i have dataits fastIts easier to use it
A86: 46178 | B86: NAIROBI | C86: NAIROBI EAST | D86: EMBAKASI | E86: TUMAINI PRIMARY AND JUNIOR SCHOOL | F86: =LEN(E86) -> 33 | G86: SL/SC | H86: Online (Link) | I86: Very Good | J86: Good | K86: =IF(I86="Very Good",4,IF(I86="Good",3,IF(I86="Poor",2,IF(I86="Very Poor",1,"")))) -> 4 | L86: =IF(J86="Very Good",4,IF(J86="Good",3,IF(J86="Poor",2,IF(J86="Very Poor",1,"")))) -> 3 | M86: =IF(OR(I86="Poor",I86="Very Poor"),"YES","") | N86: Everything was smooth I liked the fact that the progress is saved so you don't have to start afresh incase I exit abruptly | P86: I don't think any improvement is needed
A87: 46178 | B87: NAIROBI | C87: NAIROBI WEST | D87: KIBRA WESTLANDS | E87: AGA KHAN PRIMARY SCHOOL | F87: =LEN(E87) -> 23 | G87: SL/SC | H87: Online (Link) | I87: Good | J87: Good | K87: =IF(I87="Very Good",4,IF(I87="Good",3,IF(I87="Poor",2,IF(I87="Very Poor",1,"")))) -> 3 | L87: =IF(J87="Very Good",4,IF(J87="Good",3,IF(J87="Poor",2,IF(J87="Very Poor",1,"")))) -> 3 | M87: =IF(OR(I87="Poor",I87="Very Poor"),"YES","") | N87: Well documented | O87: Some few challenges when it came to uploading of documents | P87: can improve on the process especially uploading of documents
A88: 46178 | B88: NAIROBI | C88: NAIROBI WEST | D88: KIBRA WESTLANDS | E88: RAILA EDUCATIOL CENTRE | F88: =LEN(E88) -> 22 | G88: SL/SC | H88: Online (Link) | I88: Good | J88: Very Good | K88: =IF(I88="Very Good",4,IF(I88="Good",3,IF(I88="Poor",2,IF(I88="Very Poor",1,"")))) -> 3 | L88: =IF(J88="Very Good",4,IF(J88="Good",3,IF(J88="Poor",2,IF(J88="Very Poor",1,"")))) -> 4 | M88: =IF(OR(I88="Poor",I88="Very Poor"),"YES","") | N88: The whole process was easy to understand and fill in | O88: Do away with the school coordites May it apply only on a new school that is beginning the program Can include a section where buy we do a survey on how many students at school level are registered under the program | P88: I was suggesting that moving forward that under the baseline population of a school you indicated for us the number That is the previous term population to help us compare the previous term and the current term
A89: 46178 | B89: KIAMBU | C89: KIAMBU WEST | D89: KIKUYU | E89: PCEA THOGOTO PRIMARY AND JUNIOR SCHOOL | F89: =LEN(E89) -> 38 | G89: SL/SC | H89: Offline (Used the app) | I89: Good | J89: Good | K89: =IF(I89="Very Good",4,IF(I89="Good",3,IF(I89="Poor",2,IF(I89="Very Poor",1,"")))) -> 3 | L89: =IF(J89="Very Good",4,IF(J89="Good",3,IF(J89="Poor",2,IF(J89="Very Poor",1,"")))) -> 3 | M89: =IF(OR(I89="Poor",I89="Very Poor"),"YES","") | N89: The form was user friendly It guided | O89: yet | P89: yet
A90: 46178 | B90: NAIROBI | C90: NAIROBI EAST | D90: EASTLEIGH STAREHE | E90: HURUMA PRIMARY AND JUNIOR SECONDARY SCHOOL | F90: =LEN(E90) -> 42 | G90: SL/SC | H90: Online (Link) | I90: Very Good | J90: Very Good | K90: =IF(I90="Very Good",4,IF(I90="Good",3,IF(I90="Poor",2,IF(I90="Very Poor",1,"")))) -> 4 | L90: =IF(J90="Very Good",4,IF(J90="Good",3,IF(J90="Poor",2,IF(J90="Very Poor",1,"")))) -> 4 | M90: =IF(OR(I90="Poor",I90="Very Poor"),"YES","") | N90: It's very fast and accurate very easy to use | O90: It took a little longer when collecting the longitudes and latitudes | P90: May be next time we take the longitudes and latitudes from from the shades | Q90: It's accuracy is top notch
A91: 46178 | B91: NAIROBI | C91: NAIROBI WEST | D91: KIBRA WESTLANDS | E91: MILIMANI SCHOOL PRIMARY AND JUNIOR SECONDARY SCHOOL | F91: =LEN(E91) -> 51 | G91: SL/SC | H91: Online (Link) | I91: Very Good | J91: Very Good | K91: =IF(I91="Very Good",4,IF(I91="Good",3,IF(I91="Poor",2,IF(I91="Very Poor",1,"")))) -> 4 | L91: =IF(J91="Very Good",4,IF(J91="Good",3,IF(J91="Poor",2,IF(J91="Very Poor",1,"")))) -> 4 | M91: =IF(OR(I91="Poor",I91="Very Poor"),"YES","") | N91: The link is fast and efficient | O91: I feel like the form is perfect the way it is because it's easier to fill | P91: I feel the form is perfect the way it is because it's fast
A92: 46178 | B92: MOMBASA | C92: COAST | D92: NYALI MOMBASA | E92: KENGELENI PRIMARY SCHOOL | F92: =LEN(E92) -> 24 | G92: SL/SC | H92: Offline (Used the app) | I92: Very Good | J92: Very Good | K92: =IF(I92="Very Good",4,IF(I92="Good",3,IF(I92="Poor",2,IF(I92="Very Poor",1,"")))) -> 4 | L92: =IF(J92="Very Good",4,IF(J92="Good",3,IF(J92="Poor",2,IF(J92="Very Poor",1,"")))) -> 4 | M92: =IF(OR(I92="Poor",I92="Very Poor"),"YES","") | N92: Every step was leading to the next All went well | O92: During submission it indicated that my file had an error Later on I noticed that I did not download a new form thereafter I was able to submit my findings | P92: I didn't not any point of improvement | Q92: I suggest that the program baseline should be stored online to avoid distortion when new admins assumes office
A93: 46178 | B93: KISUMU | C93: WESTERN KISUMU | D93: KISUMU | E93: KOSAWO PRIMARY ECDE EYE AND JUNIOR SECONDARY SCHOOL | F93: =LEN(E93) -> 51 | G93: SL/SC | H93: Online (Link) | I93: Very Good | J93: Good | K93: =IF(I93="Very Good",4,IF(I93="Good",3,IF(I93="Poor",2,IF(I93="Very Poor",1,"")))) -> 4 | L93: =IF(J93="Very Good",4,IF(J93="Good",3,IF(J93="Poor",2,IF(J93="Very Poor",1,"")))) -> 3 | M93: =IF(OR(I93="Poor",I93="Very Poor"),"YES","") | N93: The administration was cooperate | P93: everything is okay | Q93: The Kobo app can be improved to make it more accessible and easier to use
A94: 46178 | B94: KIAMBU | C94: KIAMBU CENTRAL | D94: LIMURU 1 | E94: BIBIRIONI PRIMARY SCHOOL | F94: =LEN(E94) -> 24 | G94: SL/SC | H94: Online (Link) | I94: Very Good | J94: Very Good | K94: =IF(I94="Very Good",4,IF(I94="Good",3,IF(I94="Poor",2,IF(I94="Very Poor",1,"")))) -> 4 | L94: =IF(J94="Very Good",4,IF(J94="Good",3,IF(J94="Poor",2,IF(J94="Very Poor",1,"")))) -> 4 | M94: =IF(OR(I94="Poor",I94="Very Poor"),"YES","") | N94: Data collection was smooth as the admin was cooperative and supportive I was able to cross checked the data given and it was very accurate | O94: When browsing for a supportive document maybe you allow CamScanner because I had More than one document which need to be uploaded | P94: A feature where we can access the record of the school population since the start of the program now the we have been uploading school population in a termly basis | Q94: An overall grade attendance when doing daily attendance because recording grade per grade girls and boys takes a lot of time
A95: 46178 | B95: KIAMBU | C95: KIAMBU WEST | D95: KIKUYU | E95: KERWA PRIMARY AND JUNIOR SCHOOL | F95: =LEN(E95) -> 31 | G95: SL/SC | H95: Online (Link) | I95: Good | J95: Good | K95: =IF(I95="Very Good",4,IF(I95="Good",3,IF(I95="Poor",2,IF(I95="Very Poor",1,"")))) -> 3 | L95: =IF(J95="Very Good",4,IF(J95="Good",3,IF(J95="Poor",2,IF(J95="Very Poor",1,"")))) -> 3 | M95: =IF(OR(I95="Poor",I95="Very Poor"),"YES","") | N95: The data collection was completed within the required timeline The school magement collaborated effectively throughout the exercise | O95: Network challenges occasiolly delayed data collection | P95: Provide offline data collection guidelines
A96: 46178 | B96: KIAMBU | C96: KIAMBU CENTRAL | D96: LIMURU 1 | E96: GITUTHA PRIMARY SCHOOL | F96: =LEN(E96) -> 22 | G96: SL/SC | H96: Online (Link) | I96: Good | J96: Very Good | K96: =IF(I96="Very Good",4,IF(I96="Good",3,IF(I96="Poor",2,IF(I96="Very Poor",1,"")))) -> 3 | L96: =IF(J96="Very Good",4,IF(J96="Good",3,IF(J96="Poor",2,IF(J96="Very Poor",1,"")))) -> 4 | M96: =IF(OR(I96="Poor",I96="Very Poor"),"YES","") | N96: Data even when you are offline the data does not get lost
A97: 46178 | B97: BUNGOMA | C97: WESTERN BUNGOMA | D97: BUNGOMA | E97: WEKELEKHA RC SCHOOL | F97: =LEN(E97) -> 19 | G97: SL/SC | H97: Online (Link) | I97: Good | J97: Good | K97: =IF(I97="Very Good",4,IF(I97="Good",3,IF(I97="Poor",2,IF(I97="Very Poor",1,"")))) -> 3 | L97: =IF(J97="Very Good",4,IF(J97="Good",3,IF(J97="Poor",2,IF(J97="Very Poor",1,"")))) -> 3 | M97: =IF(OR(I97="Poor",I97="Very Poor"),"YES","") | N97: Parents understanding the accounts well and how to pay | O97: For you and our bosses to work in counties and talk to parents who still have doubt | P97: By continuing educating them through there phone importance of this feeding | Q97: Good and much reliable food
A98: 46178 | B98: NAIROBI | C98: NAIROBI WEST | D98: KIBRA WESTLANDS | E98: KILIMANI PRIMARY AND JUNIOR SECONDARY SCHOOL | F98: =LEN(E98) -> 44 | G98: SL/SC | H98: Online (Link) | I98: Good | J98: Good | K98: =IF(I98="Very Good",4,IF(I98="Good",3,IF(I98="Poor",2,IF(I98="Very Poor",1,"")))) -> 3 | L98: =IF(J98="Very Good",4,IF(J98="Good",3,IF(J98="Poor",2,IF(J98="Very Poor",1,"")))) -> 3 | M98: =IF(OR(I98="Poor",I98="Very Poor"),"YES","") | N98: Everything I had no issue | P98: For me it's working fine
A99: 46178 | B99: NAIROBI | C99: NAIROBI WEST | D99: KIBRA WESTLANDS | E99: ISLAMIA COMPREHENSIVE PRIMARY | F99: =LEN(E99) -> 29 | G99: SL/SC | H99: Online (Link) | I99: Very Good | J99: Very Good | K99: =IF(I99="Very Good",4,IF(I99="Good",3,IF(I99="Poor",2,IF(I99="Very Poor",1,"")))) -> 4 | L99: =IF(J99="Very Good",4,IF(J99="Good",3,IF(J99="Poor",2,IF(J99="Very Poor",1,"")))) -> 4 | M99: =IF(OR(I99="Poor",I99="Very Poor"),"YES","") | N99: The collection tool was easier to use than before tool | P99: Make use of the app than the link
A100: 46178 | B100: NAIROBI | C100: NAIROBI WEST | D100: KIBRA WESTLANDS | E100: MOI AVENUE PRIMARY SCHOOL | F100: =LEN(E100) -> 25 | G100: SL/SC | H100: Online (Link) | I100: Good | J100: Very Good | K100: =IF(I100="Very Good",4,IF(I100="Good",3,IF(I100="Poor",2,IF(I100="Very Poor",1,"")))) -> 3 | L100: =IF(J100="Very Good",4,IF(J100="Good",3,IF(J100="Poor",2,IF(J100="Very Poor",1,"")))) -> 4 | M100: =IF(OR(I100="Poor",I100="Very Poor"),"YES","") | N100: It's user friendlyEasier to input data
...

Sheet Pivot Tables
E3: Count of School | F3: Column Labels | L3: Count of School | M3: Column Labels | Q3: Count of School | R3: Column Labels
E4: Row Labels | F4: Good | G4: Very Good | H4: Poor | I4: Very Poor | J4: Grand Total | L4: Row Labels | M4: Offline (Used the app) | N4: Online (Link) | O4: Grand Total | Q4: Row Labels | R4: Good | S4: Poor | T4: Very Good | U4: Very Poor | V4: Grand Total
E5: NAKURU | F5: 2 | G5: 1 | J5: 3 | L5: WESTERN NAKURU | M5: 2 | N5: 1 | O5: 3 | Q5: SL/SC | R5: 233 | S5: 5 | T5: 188 | U5: 2 | V5: 428
E6: MACHAKOS | F6: 3 | G6: 1 | J6: 4 | L6: WESTERN KAKAMEGA | M6: 25 | N6: 1 | O6: 26 | Q6: KO | R6: 51 | S6: 1 | T6: 22 | U6: 1 | V6: 75
E7: KAJIADO | F7: 4 | G7: 2 | J7: 6 | L7: WESTERN BUNGOMA | M7: 18 | N7: 11 | O7: 29 | Q7: Server | R7: 37 | S7: 2 | T7: 10 | U7: 1 | V7: 50
E8: NYERI | F8: 8 | G8: 3 | H8: 2 | J8: 13 | L8: COAST | M8: 11 | N8: 12 | O8: 23 | Q8: Highschool Tapper | R8: 27 | T8: 8 | U8: 1 | V8: 36
E9: KISUMU | F9: 10 | G9: 11 | J9: 21 | L9: DECENTRALIZED CENTRAL NYERI | N9: 13 | O9: 13 | Q9: Grand Total | R9: 348 | S9: 8 | T9: 228 | U9: 5 | V9: 589
E10: MOMBASA | F10: 11 | G10: 12 | J10: 23 | L10: WESTERN KISUMU | M10: 8 | N10: 13 | O10: 21
E11: KAKAMEGA | F11: 13 | G11: 13 | J11: 26 | L11: KIAMBU EAST | M11: 16 | N11: 19 | O11: 35
E12: BUNGOMA | F12: 16 | G12: 13 | J12: 29 | L12: WESTERN UASINGISHU | M12: 21 | N12: 25 | O12: 46
E13: UASINGISHU | F13: 31 | G13: 15 | J13: 46 | L13: KIAMBU WEST | M13: 14 | N13: 35 | O13: 49
E14: MURANG'A | F14: 47 | G14: 11 | H14: 1 | I14: 2 | J14: 61 | L14: DECENTRALIZED CENTRAL MURANG'A | M14: 6 | N14: 55 | O14: 61 | Q14: Row Labels | R14: Sum of Total Score | S14: Sum of Process score
E15: KIAMBU | F15: 96 | G15: 69 | H15: 1 | I15: 1 | J15: 167 | L15: KIAMBU CENTRAL | M15: 13 | N15: 70 | O15: 83 | Q15: 4 | R15: 1128 | S15: 1040
E16: NAIROBI | F16: 107 | G16: 77 | H16: 4 | I16: 2 | J16: 190 | L16: NAIROBI WEST | M16: 13 | N16: 77 | O16: 90 | Q16: 3 | R16: 888 | S16: 913
E17: Grand Total | F17: 348 | G17: 228 | H17: 8 | I17: 5 | J17: 589 | L17: NAIROBI EAST | M17: 5 | N17: 105 | O17: 110 | Q17: 2 | R17: 14 | S17: 18
L18: Grand Total | M18: 152 | N18: 437 | O18: 589 | Q18: 1 | R18: 4 | S18: 6
Q19: Grand Total | R19: 2034 | S19: 1977
E20: Row Labels | F20: Average of Process score | L20: Count of School | M20: Column Labels
E21: NYERI | F21: 3.0769231 | L21: Row Labels | N21: YES | O21: Grand Total
E22: MURANG'A | F22: 3.0983607 | L22: BUNGOMA | M22: 29 | O22: 29
E23: MACHAKOS | F23: 3.25 | L23: KAJIADO | M23: 6 | O23: 6
E24: UASINGISHU | F24: 3.326087 | L24: KAKAMEGA | M24: 26 | O24: 26
E25: KAJIADO | F25: 3.3333333 | L25: KIAMBU | M25: 165 | N25: 2 | O25: 167
E26: NAKURU | F26: 3.3333333 | L26: KISUMU | M26: 21 | O26: 21
E27: NAIROBI | F27: 3.3631579 | L27: MACHAKOS | M27: 4 | O27: 4
E28: KIAMBU | F28: 3.3952096 | L28: MOMBASA | M28: 23 | O28: 23
E29: BUNGOMA | F29: 3.4482759 | L29: MURANG'A | M29: 58 | N29: 3 | O29: 61
E30: KAKAMEGA | F30: 3.5 | L30: NAIROBI | M30: 184 | N30: 6 | O30: 190
E31: MOMBASA | F31: 3.5217391 | L31: NAKURU | M31: 3 | O31: 3
E32: KISUMU | F32: 3.5238095 | L32: NYERI | M32: 11 | N32: 2 | O32: 13
E33: Grand Total | F33: 3.3565365 | L33: UASINGISHU | M33: 46 | O33: 46
L34: Grand Total | M34: 576 | N34: 13 | O34: 589

Sheet Dashboard 
B2: School Nutrition & Enrollment Insights — Regional Performance Dashboard
B3: Population Data Collection • Program Review • Multi-County Overview
B9: TOTAL RESPONDENTS | F9: COUNTIES COVERED | J9: POSITIVE RATING RATE | N9: FOLLOW - UP REQUIRED
B10: =GETPIVOTDATA("School ",'Pivot Tables'!$E$3) -> 589 | F10: =IF(COUNTA('Pivot Tables'!$E$4:$E$16)-2 > 1, 12, 1) -> 12 | J10: =(GETPIVOTDATA("School ",'Pivot Tables'!$E$3,"How would you rate the overall data collection process?","Very Good")+GETPIVOTDATA("School ",'Pivot Tables'!$E$3,"How would you rate the overall data collection process?","Good"))/GETPIVOTDATA("School ",'Pivot Tables'!$E$3) -> 0.97792869 | N10: =IFERROR(GETPIVOTDATA("School ",'Pivot Tables'!$L$20,"Follow-up Required","YES"),0) -> 13
B13: Field staff across Kenya | F13: Nairobi to Bungoma | J13: Good or Very Good | N13: Poor or Very Poor Rating
B16: Summary — 589 field staff completed population data collection across 12 counties. 97.8% rated the process positively. 13 schools require follow-up, with Nairobi accounting for 6 cases. Western Kakamega recorded the highest offline app usage.
K37: Follow-up required schools
K39: County | L39: Schools | M39: Priority
K40: {='Pivot Tables'!L22:L33} -> BUNGOMA | L40: {='Pivot Tables'!N22:N33} -> 0 | M40: =IF(L40>2, "Priority", "Monitor") -> Monitor
K41: KAJIADO | L41: 0 | M41: =IF(L41>2, "Priority", "Monitor") -> Monitor
K42: KAKAMEGA | L42: 0 | M42: =IF(L42>2, "Priority", "Monitor") -> Monitor
K43: KIAMBU | L43: 2 | M43: =IF(L43>2, "Priority", "Monitor") -> Monitor
K44: KISUMU | L44: 0 | M44: =IF(L44>2, "Priority", "Monitor") -> Monitor
K45: MACHAKOS | L45: 0 | M45: =IF(L45>2, "Priority", "Monitor") -> Monitor
K46: MOMBASA | L46: 0 | M46: =IF(L46>2, "Priority", "Monitor") -> Monitor
K47: MURANG'A | L47: 3 | M47: =IF(L47>2, "Priority", "Monitor") -> Priority
K48: NAIROBI | L48: 6 | M48: =IF(L48>2, "Priority", "Monitor") -> Priority
K49: NAKURU | L49: 0 | M49: =IF(L49>2, "Priority", "Monitor") -> Monitor
K50: NYERI | L50: 2 | M50: =IF(L50>2, "Priority", "Monitor") -> Monitor
K51: UASINGISHU | L51: 0 | M51: =IF(L51>2, "Priority", "Monitor") -> Monitor
